{
  "filename": "RSS_1531106786_podcast_1321_聯邦法院判決擋得了川普對等關稅嗎 2025.05.29.json",
  "episode_id": "6860fa43274ea5a738ad2419",
  "collection_name": "RSS_1531106786",
  "total_chunks": 44,
  "chunks": [
    {
      "chunk_text": "我先騎白馬走三關親愛的金曲歌后徐嘉瑩你知道現在Uber Eats上什麼東西應該都點得到嗎那點得到白馬嗎點不到但點得到白紙那濕若沙粥呢你認真嗎算了那點個螃蟹砂鍋吧在Uber Eats上你想點的都點得到應該啦",
      "chunk_id": "8d41c499-62fd-4293-89f6-495bd91e52f2",
      "chunk_index": 0,
      "episode_id": "6860fa43274ea5a738ad2419",
      "original_filename": "RSS_1531106786_podcast_1321_聯邦法院判決擋得了川普對等關稅嗎 2025.05.29.json",
      "collection_name": "RSS_1531106786",
      "chunk_length": 102,
      "enhanced_tags": [
        "愛"
      ],
      "tagged_at": "2025-07-10T14:54:57.762136"
    },
    {
      "chunk_text": "我們先來講一下輝達財報輝達今年第一季的營收是441億美元這個年比增長的幅度將近七成增長幅度非常亮眼69%69%的年比增長而且高出市場預期市場預期是432億實際是441億輝達自己的他之前的財策指引是",
      "chunk_id": "c52f73c4-f3f1-4ea0-b83c-35fb0786e1eb",
      "chunk_index": 1,
      "episode_id": "6860fa43274ea5a738ad2419",
      "original_filename": "RSS_1531106786_podcast_1321_聯邦法院判決擋得了川普對等關稅嗎 2025.05.29.json",
      "collection_name": "RSS_1531106786",
      "chunk_length": 98,
      "enhanced_tags": [
        "營收"
      ],
      "tagged_at": "2025-07-10T14:54:57.764568"
    },
    {
      "chunk_text": "421億到438億所以他也超出他財策指引的高標了前一季就去年第四季他的年比增長的幅度是78%所以你稍微要挑一些毛病的話就是說他的增長在趨緩營收雖然說非常亮眼但是跟去年第四季年比增長78%這一次放緩到69%的年比增長另外EPS是0.81美元",
      "chunk_id": "2833063b-b8d3-41b7-aed4-31361ac7d4ab",
      "chunk_index": 2,
      "episode_id": "6860fa43274ea5a738ad2419",
      "original_filename": "RSS_1531106786_podcast_1321_聯邦法院判決擋得了川普對等關稅嗎 2025.05.29.json",
      "collection_name": "RSS_1531106786",
      "chunk_length": 119,
      "enhanced_tags": [
        "營收",
        "EPS"
      ],
      "tagged_at": "2025-07-10T14:54:57.767024"
    },
    {
      "chunk_text": "但是如果剔除H20相關費用跟關稅影響之後EPS是0.96所以他把H20這個中國因素還有關稅影響把它剔除了他在會計上面做了這個版本把它剔除掉EPS是0.96這個高於上預期的0.93前一季度就是去年第四季年比增長是71%所以你稍微要再挑股頭的話",
      "chunk_id": "8d2254d4-4efb-4526-a74a-b084e3470ca8",
      "chunk_index": 3,
      "episode_id": "6860fa43274ea5a738ad2419",
      "original_filename": "RSS_1531106786_podcast_1321_聯邦法院判決擋得了川普對等關稅嗎 2025.05.29.json",
      "collection_name": "RSS_1531106786",
      "chunk_length": 120,
      "enhanced_tags": [
        "EPS",
        "關稅"
      ],
      "tagged_at": "2025-07-10T14:54:57.769436"
    },
    {
      "chunk_text": "EPS的增長也在稍微趨緩從前一季的71%到這一季33%的EPS的增長另外毛利率也受到H20的因素的影響所以他的毛利率年比大跌17.9個百分點跌到61%但是如果把H20這個因素剔除掉他毛利率回到71.371.3就跟分析師預期的71%是差不多他自己本身的財策指引是70.5",
      "chunk_id": "2b4c8906-dce4-40f7-bc92-fcd56e7c7a99",
      "chunk_index": 4,
      "episode_id": "6860fa43274ea5a738ad2419",
      "original_filename": "RSS_1531106786_podcast_1321_聯邦法院判決擋得了川普對等關稅嗎 2025.05.29.json",
      "collection_name": "RSS_1531106786",
      "chunk_length": 134,
      "enhanced_tags": [
        "EPS",
        "毛利率",
        "利率"
      ],
      "tagged_at": "2025-07-10T14:54:57.771862"
    },
    {
      "chunk_text": "到71.5所以就符合財策指引前一季度是73.5所以他比前一季度下降兩個百分點多至於說跟前一個季度跟去年第四季比下降兩個百分點多但是如果你算年比的話他下降了3.2個百分點另外還有就是營業費用營業費用有增長到35.8億年比增長了43%這可能是",
      "chunk_id": "00b5d24e-9f83-496a-9b3c-1f385d81c60d",
      "chunk_index": 5,
      "episode_id": "6860fa43274ea5a738ad2419",
      "original_filename": "RSS_1531106786_podcast_1321_聯邦法院判決擋得了川普對等關稅嗎 2025.05.29.json",
      "collection_name": "RSS_1531106786",
      "chunk_length": 119,
      "enhanced_tags": [],
      "tagged_at": "2025-07-10T14:54:57.774292"
    },
    {
      "chunk_text": "不知道他行銷人事什麼樣的費用支出所以他基本上有增長到35.8億分析師預期是36.6億所以超出市場預期至於說第二季的財策比較大的問題是營收增長不動營收只有450億因為他今年第一季是440億所以如果你算季比增幅就有兩個百分點所以這個兩個百分點跟今年第一季跟去年第四季比",
      "chunk_id": "33ab6e36-04ef-43d9-9940-f849f977429c",
      "chunk_index": 6,
      "episode_id": "6860fa43274ea5a738ad2419",
      "original_filename": "RSS_1531106786_podcast_1321_聯邦法院判決擋得了川普對等關稅嗎 2025.05.29.json",
      "collection_name": "RSS_1531106786",
      "chunk_length": 132,
      "enhanced_tags": [
        "營收"
      ],
      "tagged_at": "2025-07-10T14:54:57.776769"
    },
    {
      "chunk_text": "大概有12個百分點的季比的營收增長就差很多了另外毛利率預估是71.5到72.5分析師預估是71.7基本上大概就在七成毛利出頭一點點這個跟輝達在去年第一季毛利高達78%比其實已經下降不少就是他毛利其實有在持續下滑這也是輝達比較大的挑戰另外第二季的營業費用預估是40億美元",
      "chunk_id": "3e765f87-0a2e-41d3-a22d-05585b887274",
      "chunk_index": 7,
      "episode_id": "6860fa43274ea5a738ad2419",
      "original_filename": "RSS_1531106786_podcast_1321_聯邦法院判決擋得了川普對等關稅嗎 2025.05.29.json",
      "collection_name": "RSS_1531106786",
      "chunk_length": 134,
      "enhanced_tags": [
        "營收",
        "毛利率",
        "利率"
      ],
      "tagged_at": "2025-07-10T14:54:57.779246"
    },
    {
      "chunk_text": "這一季的38億再往上升當然營業費用升大家都知道他可能會影響略為影響他的營利率這個是在財策指引的部分Overall我自己個人覺得就是輝達未來毛利能不能維持七成是一個挑戰還有就是中國市場喫不到這個大餅實在對輝達黃教主來講也是一個非常大的傷很大的傷所以他一直在講很可惜反正黃教主電話",
      "chunk_id": "14585206-fb67-4688-870d-e7807dddac06",
      "chunk_index": 8,
      "episode_id": "6860fa43274ea5a738ad2419",
      "original_filename": "RSS_1531106786_podcast_1321_聯邦法院判決擋得了川普對等關稅嗎 2025.05.29.json",
      "collection_name": "RSS_1531106786",
      "chunk_length": 138,
      "enhanced_tags": [
        "利率"
      ],
      "tagged_at": "2025-07-10T14:54:57.781818"
    },
    {
      "chunk_text": "就一直在講說中國是一個很大的AI市場500億美元的AI規模我們喫不到怎麼樣反正就是圍繞這些話題上面但他同時也講了他的MVLink72出貨的情況非常的好一週可以有1000臺的建置等等一週我們有7萬2000顆類似這樣子這樣子有利空的一些說法就讓輝達盤後股價漲了5%帶動了美股",
      "chunk_id": "fea494a0-4d93-4025-bd87-1ea2e422799a",
      "chunk_index": 9,
      "episode_id": "6860fa43274ea5a738ad2419",
      "original_filename": "RSS_1531106786_podcast_1321_聯邦法院判決擋得了川普對等關稅嗎 2025.05.29.json",
      "collection_name": "RSS_1531106786",
      "chunk_length": 135,
      "enhanced_tags": [
        "美股",
        "AI"
      ],
      "tagged_at": "2025-07-10T14:54:57.784364"
    },
    {
      "chunk_text": "這個是在輝達的部分另外還有就是美國聯邦法院這也是一個今天重頭戲這些我們都來請教富蘭克林的梁佩琳副總經理佩琳你好佩琳你好佩琳我們先來講一下聯邦法院好了我們等一下再來講一下輝達因為輝達我剛才稍微講了一點等一下再請教你怎麼看輝達聯邦法院這個事情現在目前最新",
      "chunk_id": "5e8c3060-cadf-41c2-aa8a-6a8b0ed9b305",
      "chunk_index": 10,
      "episode_id": "6860fa43274ea5a738ad2419",
      "original_filename": "RSS_1531106786_podcast_1321_聯邦法院判決擋得了川普對等關稅嗎 2025.05.29.json",
      "collection_name": "RSS_1531106786",
      "chunk_length": 125,
      "enhanced_tags": [],
      "tagged_at": "2025-07-10T14:54:57.786865"
    },
    {
      "chunk_text": "就是說白宮已經上訴了對不對",
      "chunk_id": "3b7e0586-6c14-4a2b-8eb4-d92b03123927",
      "chunk_index": 11,
      "episode_id": "6860fa43274ea5a738ad2419",
      "original_filename": "RSS_1531106786_podcast_1321_聯邦法院判決擋得了川普對等關稅嗎 2025.05.29.json",
      "collection_name": "RSS_1531106786",
      "chunk_length": 13,
      "enhanced_tags": [
        "司法程序"
      ],
      "tagged_at": "2025-07-10T14:54:57.788950"
    },
    {
      "chunk_text": "對於中國然後還有像是就是全面的一個10%的基準關稅但是不包含就是像針對依據301的一個法條之下對於鋼鋁還有汽車25%的一個關稅的部分那剛剛其實木華提到其實白宮已經要上訴那目前未來的一個進展可能就是要經過聯邦的一個巡迴上訴法院還有在最後再上訴到最高法院那如果按照上一次川普其實在墨西哥邊境牆的部分",
      "chunk_id": "d1447771-3696-49cf-865e-790b2a51680b",
      "chunk_index": 12,
      "episode_id": "6860fa43274ea5a738ad2419",
      "original_filename": "RSS_1531106786_podcast_1321_聯邦法院判決擋得了川普對等關稅嗎 2025.05.29.json",
      "collection_name": "RSS_1531106786",
      "chunk_length": 147,
      "enhanced_tags": [
        "司法程序",
        "關稅"
      ],
      "tagged_at": "2025-07-10T14:54:57.791449"
    },
    {
      "chunk_text": "提到同樣的一個法院的一個狀況的話就是法律訴訟大概其實廢時大概將近有兩年多所以這當中的確是未來這個部分其實是還需要一些時間但是呢這是不是代表這個關稅的部分就會全面的就是不會實施那目前看起來其實在今天這個消息出來之後其實美股的期貨盤是大漲的那亞洲股市還有剛剛的歐股開盤也是大漲的一個比較上漲的狀況但最近看了出來其實最近這",
      "chunk_id": "c08c703a-52b8-4365-9b34-cfb1b1a889ad",
      "chunk_index": 13,
      "episode_id": "6860fa43274ea5a738ad2419",
      "original_filename": "RSS_1531106786_podcast_1321_聯邦法院判決擋得了川普對等關稅嗎 2025.05.29.json",
      "collection_name": "RSS_1531106786",
      "chunk_length": 158,
      "enhanced_tags": [
        "歐股",
        "關稅",
        "美股",
        "投資"
      ],
      "tagged_at": "2025-07-10T14:54:57.794018"
    },
    {
      "chunk_text": "就是這幾個",
      "chunk_id": "f2937186-99d2-4f7f-b2c1-38ced2dbc98a",
      "chunk_index": 14,
      "episode_id": "6860fa43274ea5a738ad2419",
      "original_filename": "RSS_1531106786_podcast_1321_聯邦法院判決擋得了川普對等關稅嗎 2025.05.29.json",
      "collection_name": "RSS_1531106786",
      "chunk_length": 5,
      "enhanced_tags": [],
      "tagged_at": "2025-07-10T14:54:57.796178"
    },
    {
      "chunk_text": "的部分剛提到了針對特定產業的部分因為都有陸續在做調查另外一個就是針對中國的部分能源就是針對特定的一個國家其實也都有在做調查其實還是有可能引用這樣子的法源來課徵關稅那對於就是全面關稅的部分呢有可能引用的法條是一百二十二條貿易法案的部分就是針對大額的貿易逆差國呢他最高可以課徵15%的一個關稅那他的時間是有限制的",
      "chunk_id": "b410a900-35df-411b-bc6c-357511033490",
      "chunk_index": 15,
      "episode_id": "6860fa43274ea5a738ad2419",
      "original_filename": "RSS_1531106786_podcast_1321_聯邦法院判決擋得了川普對等關稅嗎 2025.05.29.json",
      "collection_name": "RSS_1531106786",
      "chunk_length": 154,
      "enhanced_tags": [
        "貿易逆差",
        "關稅"
      ],
      "tagged_at": "2025-07-10T14:54:57.798789"
    },
    {
      "chunk_text": "就是有150天的一個狀況也就是說未來其實川普政府能做的呢有可能就是透過引用剛剛提到了相關其他個別的一個法案的一個依據那還是會有針對不同國家尤其是針對貿易逆差比較嚴峻的國家來課徵關稅但是這個相較於全面去課10%或者是更高的那個對等關稅的一個部分的確這個範圍跟幅度有可能會比原先預期來的小喔那所以其實結論就是",
      "chunk_id": "b90c756b-c4a2-4160-a91d-bb90c2d98c12",
      "chunk_index": 16,
      "episode_id": "6860fa43274ea5a738ad2419",
      "original_filename": "RSS_1531106786_podcast_1321_聯邦法院判決擋得了川普對等關稅嗎 2025.05.29.json",
      "collection_name": "RSS_1531106786",
      "chunk_length": 152,
      "enhanced_tags": [
        "貿易逆差",
        "關稅",
        "對等關稅"
      ],
      "tagged_at": "2025-07-10T14:54:57.802270"
    },
    {
      "chunk_text": "其實這部分可能沒有辦法完全如大家一開始非常樂觀期待說好像就4月2號就是回到解放日之前可能沒有辦法回到那樣的一個狀況但是至少這個比較有點警報有一點解除了啦那但是其實我想其實若以川普政府的一個立場來看的話應該還是會想辦法去做就是還是會想辦法去做一些課徵關稅的一個動作那只是說如果以下半年來看的話的確剛剛提到",
      "chunk_id": "3f9ac0eb-58bb-4830-b553-eccdcd05dd9f",
      "chunk_index": 17,
      "episode_id": "6860fa43274ea5a738ad2419",
      "original_filename": "RSS_1531106786_podcast_1321_聯邦法院判決擋得了川普對等關稅嗎 2025.05.29.json",
      "collection_name": "RSS_1531106786",
      "chunk_length": 151,
      "enhanced_tags": [
        "民事法律",
        "關稅"
      ],
      "tagged_at": "2025-07-10T14:54:57.806386"
    },
    {
      "chunk_text": "民意法條啊這部分等等的他可能或者是232他針對一些特定產業啦這部分可能都需要調查那調查的時間都是要6到9個月最後纔能夠定案對其實現在大概確定可能還是會繼續的就是鋼鋁汽車的部分這部分當然也會牽涉到現在正在進行就是已經跟美國進行關稅談判的像是日本韓國還有歐盟的部分但是其實對於整體來看的話的確有可能會比",
      "chunk_id": "9a3bfefe-4530-4b6e-8426-b8d91e02a3ce",
      "chunk_index": 18,
      "episode_id": "6860fa43274ea5a738ad2419",
      "original_filename": "RSS_1531106786_podcast_1321_聯邦法院判決擋得了川普對等關稅嗎 2025.05.29.json",
      "collection_name": "RSS_1531106786",
      "chunk_length": 149,
      "enhanced_tags": [
        "歐盟",
        "關稅"
      ],
      "tagged_at": "2025-07-10T14:54:57.810520"
    },
    {
      "chunk_text": "原先預期的其實是來的小一些那這部分也可以看得出來為什麼市場其實氣氛還是偏向比較就是比較樂觀在看待這個貿易法案法院的判決但是也沒有出現那種非常報復性的一個慶祝行情的原因",
      "chunk_id": "d15e9b35-63d5-4ab1-9d58-f1654d6d8d5b",
      "chunk_index": 19,
      "episode_id": "6860fa43274ea5a738ad2419",
      "original_filename": "RSS_1531106786_podcast_1321_聯邦法院判決擋得了川普對等關稅嗎 2025.05.29.json",
      "collection_name": "RSS_1531106786",
      "chunk_length": 83,
      "enhanced_tags": [],
      "tagged_at": "2025-07-10T14:54:57.814461"
    },
    {
      "chunk_text": "所以你不要說這個有什麼政治的問題其實基本上川普他自己有任命三個人其中一之一那另外兩個人一個是雷根任命另外是歐巴馬任命那這個美國國際貿易法院是怎麼說呢他說在10個日內要發布必要的行政命令執行永久禁令什麼永久禁令就針對這個對等關稅永久禁令他說如果到時候沒有更高法院出手幹預的話",
      "chunk_id": "f6d3d9be-2f42-4cda-af5b-97a14477e8c0",
      "chunk_index": 20,
      "episode_id": "6860fa43274ea5a738ad2419",
      "original_filename": "RSS_1531106786_podcast_1321_聯邦法院判決擋得了川普對等關稅嗎 2025.05.29.json",
      "collection_name": "RSS_1531106786",
      "chunk_length": 136,
      "enhanced_tags": [
        "關稅",
        "時事",
        "對等關稅",
        "國際貿易法"
      ],
      "tagged_at": "2025-07-10T14:54:57.818675"
    },
    {
      "chunk_text": "這個對等關稅的政策將失效但是就像剛剛佩琳所講這個裁決不影響川普根據其他法律授權徵收的關稅包括鋼 鋁 汽車這些關稅以及川普威脅對藥品半導體跟其他關鍵產品徵收的關稅所以會不會川普轉一個彎去針對半導體藥品個別產業徵收關稅反正我對國家不徵收對等關稅但是我對個別產業徵收關稅那不是換他們不換藥嗎",
      "chunk_id": "84565181-702a-4fef-8f8f-e34271c2e441",
      "chunk_index": 21,
      "episode_id": "6860fa43274ea5a738ad2419",
      "original_filename": "RSS_1531106786_podcast_1321_聯邦法院判決擋得了川普對等關稅嗎 2025.05.29.json",
      "collection_name": "RSS_1531106786",
      "chunk_length": 142,
      "enhanced_tags": [
        "關稅",
        "半導體",
        "時事",
        "對等關稅"
      ],
      "tagged_at": "2025-07-10T14:54:57.822680"
    },
    {
      "chunk_text": "那後面還有的讚那至於說川普還有什麼樣的反制呢除了剛剛講上述以外呢等一下我們講一下高盛的看法給各位聽一下我們這邊先休息一下等一下回到節目現場",
      "chunk_id": "5d134ee6-4528-467f-aeee-c2cd6e6f3395",
      "chunk_index": 22,
      "episode_id": "6860fa43274ea5a738ad2419",
      "original_filename": "RSS_1531106786_podcast_1321_聯邦法院判決擋得了川普對等關稅嗎 2025.05.29.json",
      "collection_name": "RSS_1531106786",
      "chunk_length": 69,
      "enhanced_tags": [],
      "tagged_at": "2025-07-10T14:54:57.825582"
    },
    {
      "chunk_text": "這個裁決給法院給出了四個重要結論第一個IEPA之下的總統權力有限這個IEPA是什麼呢就是國際緊急經濟權力法這個法院認為1977年IEPA不能賦予總統無限關稅權所以川普無權對任何國家以任何金額無期限的徵收關稅這是第一個也是最重要的接下來會發生什麼",
      "chunk_id": "730ad078-fb9b-4d18-a23f-acb4ac01dcb8",
      "chunk_index": 23,
      "episode_id": "6860fa43274ea5a738ad2419",
      "original_filename": "RSS_1531106786_podcast_1321_聯邦法院判決擋得了川普對等關稅嗎 2025.05.29.json",
      "collection_name": "RSS_1531106786",
      "chunk_length": 122,
      "enhanced_tags": [
        "關稅",
        "時事"
      ],
      "tagged_at": "2025-07-10T14:54:57.828105"
    },
    {
      "chunk_text": "高盛的看法是怎麼樣呢高盛最新的也有他們的報告出來了",
      "chunk_id": "442413ca-42ff-47e6-9f73-4495762ee11f",
      "chunk_index": 24,
      "episode_id": "6860fa43274ea5a738ad2419",
      "original_filename": "RSS_1531106786_podcast_1321_聯邦法院判決擋得了川普對等關稅嗎 2025.05.29.json",
      "collection_name": "RSS_1531106786",
      "chunk_length": 25,
      "enhanced_tags": [],
      "tagged_at": "2025-07-10T14:54:57.830296"
    },
    {
      "chunk_text": "反正基本上就是一個法律戰那另外值得一提的就是說相比這個萬能關稅就是國際緊急緊急權力法就是IEPA就是這一次的對等關稅是引用這個權力法所做出來的決定",
      "chunk_id": "353554f9-cae6-4e1e-93e3-062b166c16c6",
      "chunk_index": 25,
      "episode_id": "6860fa43274ea5a738ad2419",
      "original_filename": "RSS_1531106786_podcast_1321_聯邦法院判決擋得了川普對等關稅嗎 2025.05.29.json",
      "collection_name": "RSS_1531106786",
      "chunk_length": 73,
      "enhanced_tags": [
        "關稅",
        "時事",
        "對等關稅"
      ],
      "tagged_at": "2025-07-10T14:54:57.832601"
    },
    {
      "chunk_text": "所以高盛最後認為說",
      "chunk_id": "bc331315-ea95-4b11-a78e-c868271a8591",
      "chunk_index": 26,
      "episode_id": "6860fa43274ea5a738ad2419",
      "original_filename": "RSS_1531106786_podcast_1321_聯邦法院判決擋得了川普對等關稅嗎 2025.05.29.json",
      "collection_name": "RSS_1531106786",
      "chunk_length": 9,
      "enhanced_tags": [],
      "tagged_at": "2025-07-10T14:54:57.834679"
    },
    {
      "chunk_text": "貿易順差的國家在150天期限屆滿之後不會面臨基準關稅那這不是包括我們在內了嗎是不是佩玲是這樣嗎對應該是說他就是會針對上限15%然後150天那個只能針對就是他的貿易逆差是非常嚴峻的國家貿易較小那我們是嚴峻我們600億700億算嚴峻",
      "chunk_id": "90878178-8bf8-44a4-997b-a9fb1cfb89a7",
      "chunk_index": 27,
      "episode_id": "6860fa43274ea5a738ad2419",
      "original_filename": "RSS_1531106786_podcast_1321_聯邦法院判決擋得了川普對等關稅嗎 2025.05.29.json",
      "collection_name": "RSS_1531106786",
      "chunk_length": 114,
      "enhanced_tags": [
        "貿易逆差",
        "貿易順差",
        "關稅"
      ],
      "tagged_at": "2025-07-10T14:54:57.837190"
    },
    {
      "chunk_text": "應該是說像比方說像英國啦或者是歐盟那種就相對有可能是可以避開的這樣子那這不就是隻針對了貿易逆差在500億美元以上那就包括中國大陸還有我們還有加拿大中國大陸會依據301法案做調查所以未來其實就變成剛剛木華哥提到了其實就是真的還是有很多不確定性所以可以看到市場有",
      "chunk_id": "db2273eb-862a-4553-97dc-5e28063e4c89",
      "chunk_index": 28,
      "episode_id": "6860fa43274ea5a738ad2419",
      "original_filename": "RSS_1531106786_podcast_1321_聯邦法院判決擋得了川普對等關稅嗎 2025.05.29.json",
      "collection_name": "RSS_1531106786",
      "chunk_length": 129,
      "enhanced_tags": [
        "貿易逆差",
        "歐盟"
      ],
      "tagged_at": "2025-07-10T14:54:57.839675"
    },
    {
      "chunk_text": "歡喜一陣子但是現在的情緒又比較恢復比較冷靜一點對這其實從那個美債殖利率可以看到這樣的現象對不對現在目前大家不要以為美債殖利率是下去喔不對喔現在目前美債殖利率是全面走高喔那市場認為這次關稅的叫停並不見得完全是利多它反而暴露了美國政治協調性的崩塌尤其是關稅政策是被司法部門而非行政立法部門叫停的",
      "chunk_id": "fceeb175-b8f9-481e-8360-61d208f181c8",
      "chunk_index": 29,
      "episode_id": "6860fa43274ea5a738ad2419",
      "original_filename": "RSS_1531106786_podcast_1321_聯邦法院判決擋得了川普對等關稅嗎 2025.05.29.json",
      "collection_name": "RSS_1531106786",
      "chunk_length": 145,
      "enhanced_tags": [
        "情緒",
        "健康",
        "利率",
        "關稅",
        "時事"
      ],
      "tagged_at": "2025-07-10T14:54:57.842441"
    },
    {
      "chunk_text": "他這種印象就是說反正行政跟司法部之間的一個衝突他說宏觀經濟的傳播現在目前是無人掌舵在財政前景堪憂之下關稅叫停帶來的潛在財政收入反而加劇市場對美國藏在能力的質疑也就是說反而大家都覺得說關稅現在乾稅我們剛剛昨天節目有講他現在一個月已經收到幾百億了對不對所以如果說這個關稅沒有了那不是美國現在財政更麻煩還有大美利方案",
      "chunk_id": "1026a3e7-c536-4e49-8012-753df7e458fe",
      "chunk_index": 30,
      "episode_id": "6860fa43274ea5a738ad2419",
      "original_filename": "RSS_1531106786_podcast_1321_聯邦法院判決擋得了川普對等關稅嗎 2025.05.29.json",
      "collection_name": "RSS_1531106786",
      "chunk_length": 155,
      "enhanced_tags": [
        "關稅",
        "時事"
      ],
      "tagged_at": "2025-07-10T14:54:57.845108"
    },
    {
      "chunk_text": "對其實如果從聯準會今天最新的利率決策會議的紀錄也透露出這個就是但他除了提到了關稅就是企業要轉嫁給消費者那甚至有一些沒有收到關稅影響的企業有可能會趁機漲價所以其實聯準會官員對於通膨這一塊關稅造成的通膨其實是比較謹慎的也就是意味著短期內不會有降息的一個可能性那另外一個就是也提到說因為整個川普",
      "chunk_id": "3dea31b0-ff01-4c94-b846-26632457bfb8",
      "chunk_index": 31,
      "episode_id": "6860fa43274ea5a738ad2419",
      "original_filename": "RSS_1531106786_podcast_1321_聯邦法院判決擋得了川普對等關稅嗎 2025.05.29.json",
      "collection_name": "RSS_1531106786",
      "chunk_length": 144,
      "enhanced_tags": [
        "職涯",
        "通膨",
        "利率",
        "關稅",
        "降息",
        "權利保障"
      ],
      "tagged_at": "2025-07-10T14:54:57.847616"
    },
    {
      "chunk_text": "發動的貿易戰的確讓過去就是美國資產被視為是避險就是安全港的地位的確是面臨到很大的挑戰從過去一段時間整個美元的一個不論是美國終結論引發結束引發美國的一個例外論的一個結束引發著整個就是大家拋售美元資產等等的這樣子的因素的確都造成整個在整個聯準會的部分也是有提關心到這樣子的一個擔憂啦那這部分",
      "chunk_id": "251402b6-3ecd-4270-b813-711d5b450a0b",
      "chunk_index": 32,
      "episode_id": "6860fa43274ea5a738ad2419",
      "original_filename": "RSS_1531106786_podcast_1321_聯邦法院判決擋得了川普對等關稅嗎 2025.05.29.json",
      "collection_name": "RSS_1531106786",
      "chunk_length": 143,
      "enhanced_tags": [
        "貿易戰",
        "權利保障",
        "投資",
        "避險"
      ],
      "tagged_at": "2025-07-10T14:54:57.850111"
    },
    {
      "chunk_text": "我覺得的確是為什麼其實在現階段來看的話",
      "chunk_id": "b2b1d31b-3879-4e80-a78a-9e4c2637a0bc",
      "chunk_index": 33,
      "episode_id": "6860fa43274ea5a738ad2419",
      "original_filename": "RSS_1531106786_podcast_1321_聯邦法院判決擋得了川普對等關稅嗎 2025.05.29.json",
      "collection_name": "RSS_1531106786",
      "chunk_length": 19,
      "enhanced_tags": [],
      "tagged_at": "2025-07-10T14:54:57.852248"
    },
    {
      "chunk_text": "這個當然我覺得如果現階段因為整個就是從美中的一個關稅還是在一個休兵的狀態現在看起來其實大家都還是在積極的",
      "chunk_id": "3d51beff-34b8-4937-a0ab-f2bf40f9ca05",
      "chunk_index": 34,
      "episode_id": "6860fa43274ea5a738ad2419",
      "original_filename": "RSS_1531106786_podcast_1321_聯邦法院判決擋得了川普對等關稅嗎 2025.05.29.json",
      "collection_name": "RSS_1531106786",
      "chunk_length": 52,
      "enhanced_tags": [
        "關稅"
      ],
      "tagged_at": "2025-07-10T14:54:57.854565"
    },
    {
      "chunk_text": "拉貨的狀態那尤其其實整體的美國經濟其實如果以硬數據來看的話其實都還是屬於蠻穩健的一個狀況所以我們覺得如果以美國股市我們覺得還是有機會去挑戰前波的歷史新高那只是如果你就是譚普白指數的確在六千點附近看起來有一點整數關卡的壓力啊那這部分我們覺得還是有機會去震盪走尖債券市場當然比較影響美股另外一個因素就是在於債券值利率的部分",
      "chunk_id": "6fdd752a-b308-425f-816d-2f01383414f7",
      "chunk_index": 35,
      "episode_id": "6860fa43274ea5a738ad2419",
      "original_filename": "RSS_1531106786_podcast_1321_聯邦法院判決擋得了川普對等關稅嗎 2025.05.29.json",
      "collection_name": "RSS_1531106786",
      "chunk_length": 159,
      "enhanced_tags": [
        "美股",
        "健康",
        "利率",
        "投資",
        "時事"
      ],
      "tagged_at": "2025-07-10T14:54:57.857174"
    },
    {
      "chunk_text": "加在的是看到這一波債券值利率的反彈這當中的壓力主要還是在集中在常債那就是二十年跟三十年期目前都在5個%附近但是就短債的部分其實反而是呈現比較穩定的狀態這也是呼應我們其實富蘭克林集團其實一再側重的就是我們目前是比較偏重在短中天期債的部分就是不要去因為常債的部分就面臨到就是在債務上限的問題等等還有因為美國經濟",
      "chunk_id": "cd86a60d-d8ae-4731-89c6-c40854c7493f",
      "chunk_index": 36,
      "episode_id": "6860fa43274ea5a738ad2419",
      "original_filename": "RSS_1531106786_podcast_1321_聯邦法院判決擋得了川普對等關稅嗎 2025.05.29.json",
      "collection_name": "RSS_1531106786",
      "chunk_length": 153,
      "enhanced_tags": [
        "健康",
        "利率",
        "投資",
        "時事",
        "反彈"
      ],
      "tagged_at": "2025-07-10T14:54:57.859819"
    },
    {
      "chunk_text": "衰退的經濟降低當然就是美債美國常債當然就是會有攀升的一個部分再加上有通膨的一個擔憂等等的所以現階段的債券會比較建議在短債那股市的部分我們覺得還是有機會去挑戰前波的一個歷史新高好那回答財報您的看法這是我是覺得他的毛利呢各方面其實是有一些成長壓力的了對當然其實經歷了過去一兩年的一個高的機器",
      "chunk_id": "d3d2c5ae-48dd-4e35-b001-c2519de1d44d",
      "chunk_index": 37,
      "episode_id": "6860fa43274ea5a738ad2419",
      "original_filename": "RSS_1531106786_podcast_1321_聯邦法院判決擋得了川普對等關稅嗎 2025.05.29.json",
      "collection_name": "RSS_1531106786",
      "chunk_length": 143,
      "enhanced_tags": [
        "健康",
        "通膨",
        "家庭",
        "投資",
        "時事"
      ],
      "tagged_at": "2025-07-10T14:54:57.862445"
    },
    {
      "chunk_text": "而且高速成長之後的機器墊高了我覺得現階段看起來的一個成長放緩我們覺得是意料中式那只是說這當中基本上我們覺得他這一次算交出來的財報其實真的還算是就是應該是還算是真的蠻正面的那最主要還是在於說其實他不論是第一季的有部分受到就是中國的一個營收的影響那第二季這一季的財策也是類似的一個狀況那我覺得對輝達來說",
      "chunk_id": "66558dde-c6d1-4c03-8032-07dfddcee547",
      "chunk_index": 38,
      "episode_id": "6860fa43274ea5a738ad2419",
      "original_filename": "RSS_1531106786_podcast_1321_聯邦法院判決擋得了川普對等關稅嗎 2025.05.29.json",
      "collection_name": "RSS_1531106786",
      "chunk_length": 149,
      "enhanced_tags": [
        "營收",
        "家庭"
      ],
      "tagged_at": "2025-07-10T14:54:57.865096"
    },
    {
      "chunk_text": "我也贊成木華提到了就是他要維持未來的毛利率還是要維持在相對的就是七成附近另外一個就是我覺得他最近推出來了就是NVLink這一個其實很大的一個我覺得是中長線是一個比較大的利多因為他把過去可能是他的競爭對手的部分都融入到他的生態圈那這部分其實會讓他未來的一個整體持續的一個大者很大那我覺得他釋放出來的訊息還是在於不論是資料中心等等",
      "chunk_id": "d2b57d9e-d4ba-432b-9245-e4dccddf42e8",
      "chunk_index": 39,
      "episode_id": "6860fa43274ea5a738ad2419",
      "original_filename": "RSS_1531106786_podcast_1321_聯邦法院判決擋得了川普對等關稅嗎 2025.05.29.json",
      "collection_name": "RSS_1531106786",
      "chunk_length": 163,
      "enhanced_tags": [
        "毛利率",
        "利率"
      ],
      "tagged_at": "2025-07-10T14:54:57.867726"
    },
    {
      "chunk_text": "他對於AI的基礎建設的需求基本上還是蠻強勁沒有像過去大家很擔心的說好像會很急速的一個放緩甚至會擔心就是你在AI投資上沒有辦法轉化成獲利的這一塊那我覺得輝達在這一部分尤其是在NVLink這個生態圈的一個發展之下其實未來我覺得他的一個在AI轉型成AI基礎建設公司這部分是佔有很大的領先優勢的所以基本上我們還是對於整個AI",
      "chunk_id": "f857df84-824e-4512-9d93-d993347efead",
      "chunk_index": 40,
      "episode_id": "6860fa43274ea5a738ad2419",
      "original_filename": "RSS_1531106786_podcast_1321_聯邦法院判決擋得了川普對等關稅嗎 2025.05.29.json",
      "collection_name": "RSS_1531106786",
      "chunk_length": 158,
      "enhanced_tags": [
        "職涯",
        "投資",
        "時事",
        "AI",
        "權利保障"
      ],
      "tagged_at": "2025-07-10T14:54:57.870273"
    },
    {
      "chunk_text": "輝達這部分的前景還是抱以比較正面的一個看待好那另外一個消息就是韓國央行今天再次降息是四連降而且下調經濟預期預計還有更多的降息可見韓國的經濟情況真的很差韓國把今年的GDP增長大幅下調到只有0.8所以下半年看起來全世界經濟增長都遇到一些問題昨天足跡總處也預估出來下半年的經濟增長只有1%雖然說今年還有3%多的",
      "chunk_id": "6e7db7e6-4beb-4ffd-aa98-e66d4798b9e1",
      "chunk_index": 41,
      "episode_id": "6860fa43274ea5a738ad2419",
      "original_filename": "RSS_1531106786_podcast_1321_聯邦法院判決擋得了川普對等關稅嗎 2025.05.29.json",
      "collection_name": "RSS_1531106786",
      "chunk_length": 152,
      "enhanced_tags": [
        "降息",
        "GDP",
        "時事"
      ],
      "tagged_at": "2025-07-10T14:54:57.872918"
    },
    {
      "chunk_text": "經濟增長是上半年5%多的貢獻所以佩玲是不是下半年整個全球的GDP你從今天韓國跟昨天足跡總處預估下半年臺灣的經濟增長就1%可以看到這樣狀況的確我們也認為今年的全球經濟有可能是上半年比較強因為就是在關稅暫停然後拉貨潮的帶動但下半年終端的需求是不是可以真的去消化現在拉貨的一個累積的庫存這部分可能再加上整體的景氣循環",
      "chunk_id": "dbf13d7e-ef48-4666-9867-c6c2b3ccedb7",
      "chunk_index": 42,
      "episode_id": "6860fa43274ea5a738ad2419",
      "original_filename": "RSS_1531106786_podcast_1321_聯邦法院判決擋得了川普對等關稅嗎 2025.05.29.json",
      "collection_name": "RSS_1531106786",
      "chunk_length": 155,
      "enhanced_tags": [
        "景氣循環",
        "關稅",
        "GDP",
        "時事"
      ],
      "tagged_at": "2025-07-10T14:54:57.875442"
    },
    {
      "chunk_text": "也走到了相對末期的部分所以目前像看到了經濟成長率的預估可能今年的第三到第四季是相對的谷底但好消息是不至於會陷入到衰退即便像是美國的部分都還是有非常低的溫和症成長所以投資人倒也不用這麼的一個悲觀OK非常謝謝梁佩玲那我們這邊先休息一下等一下回到我們節目現場",
      "chunk_id": "1619de5a-a0ed-4046-bf22-8ab133e46228",
      "chunk_index": 43,
      "episode_id": "6860fa43274ea5a738ad2419",
      "original_filename": "RSS_1531106786_podcast_1321_聯邦法院判決擋得了川普對等關稅嗎 2025.05.29.json",
      "collection_name": "RSS_1531106786",
      "chunk_length": 126,
      "enhanced_tags": [
        "家庭",
        "投資",
        "經濟成長率",
        "時事"
      ],
      "tagged_at": "2025-07-10T14:54:57.877942"
    }
  ],
  "original_text_length": 5246,
  "enhanced_tagging_info": {
    "processor": "EnhancedTagProcessor",
    "tagged_at": "2025-07-10T14:54:57.877948",
    "total_chunks": 44,
    "total_tags": 103
  }
}