{
  "filename": "RSS_1500839292_podcast_1321_EP308 _ .json",
  "episode_id": "6864df05b8a9f5c81761b4b5",
  "collection_name": "RSS_1500839292",
  "total_chunks": 100,
  "chunks": [
    {
      "chunk_text": "歡迎收聽谷外,我是神木工,本集節目由知識衛星贊助。",
      "chunk_id": "e746a182-fbb6-4dff-bc82-c6d7944f5c39",
      "chunk_index": 0,
      "episode_id": "6864df05b8a9f5c81761b4b5",
      "original_filename": "RSS_1500839292_podcast_1321_EP308 _ .json",
      "collection_name": "RSS_1500839292",
      "chunk_length": 25
    },
    {
      "chunk_text": "有名詞和知識,也讓大朋友小朋友提早認識未來人生的重大決策,如上班、買賣、借貸、存款和股票投資等等。由全台最好的財務教學品牌超級數字力推出理財桌遊包含實體桌遊產品加100分鐘的影音課程募資期間12月15號到1月22號優於65折,輸入谷外專屬的折扣碼谷外桌遊4個字,還多折300塊。好玩又長知識的最佳選擇,從遊戲展開自身與小朋友的共同思考和對話。",
      "chunk_id": "f35fe266-8a94-4554-8141-dcadb5c43c5e",
      "chunk_index": 1,
      "episode_id": "6864df05b8a9f5c81761b4b5",
      "original_filename": "RSS_1500839292_podcast_1321_EP308 _ .json",
      "collection_name": "RSS_1500839292",
      "chunk_length": 171
    },
    {
      "chunk_text": "推薦給所有有需要的朋友們。",
      "chunk_id": "6f93c638-8287-4250-8808-8026dddd3472",
      "chunk_index": 2,
      "episode_id": "6864df05b8a9f5c81761b4b5",
      "original_filename": "RSS_1500839292_podcast_1321_EP308 _ .json",
      "collection_name": "RSS_1500839292",
      "chunk_length": 13
    },
    {
      "chunk_text": "我是一個對於節日很不敏感的人,當然也不是那種裝逼仔,有些裝逼仔就是聖誕節、情人節,那個就是商人的陰謀。這種就是派對上最有趣的人,別人都不知道,就你最厲害。不是這樣的想法,就是你根本不會想到說有節日在那邊,你就單純的真的忘掉這件事情。只是像我這樣的一個思維方式呢,我跟我老婆溝通,她是無法理解,她覺得我就是沒有用心,你就是一個廢物。",
      "chunk_id": "e5f76225-34f6-4aef-b68d-00494ee83854",
      "chunk_index": 3,
      "episode_id": "6864df05b8a9f5c81761b4b5",
      "original_filename": "RSS_1500839292_podcast_1321_EP308 _ .json",
      "collection_name": "RSS_1500839292",
      "chunk_length": 165
    },
    {
      "chunk_text": "那在婚後呢,我覺得開始有慢慢改善這一件事情。至少以過去的兩年多來看,我沒有忘記她的生日,也沒有忘記結婚紀念日,那我兒子的生日到了我也還記得。但是當然像去年結婚紀念日是前一天我老婆提醒我,我才想到她暗示,然後才想到我這樣的事情。所以呢,我開始對節日比較用心一點,因為我覺得這兩個人的事情啊,就如果說你自己不在意,那你老婆也不在意,那就沒關係。可是如果說你老婆在意,你自己不在意,",
      "chunk_id": "668f6989-d94a-4ff6-bcd9-3dbdd4d9ba08",
      "chunk_index": 4,
      "episode_id": "6864df05b8a9f5c81761b4b5",
      "original_filename": "RSS_1500839292_podcast_1321_EP308 _ .json",
      "collection_name": "RSS_1500839292",
      "chunk_length": 188
    },
    {
      "chunk_text": "你只要跟著在意,因為要互相尊重啊,她在意的東西你就要稍微在意一下。那不然像你平常跟她講一些有沒有股票的東西,她還可以完全不屌你啊,一樣的道理,就互相尊重。那聖誕節在我心目中開始變成一個重大的節日呢,差不多是兩年前。我們以前在台北市住小套房的時候,就有一個小聖誕樹,然後後來在我伯父的邀請之下說,你不要住台北啊,那那麼小又那麼貴,你到林口差不多價格,你看大這麼多,從本來四坪含廁所變成在林口可以住到一個17、18坪的,",
      "chunk_id": "450230a0-2fad-4ec0-bf91-fab24b1cee60",
      "chunk_index": 5,
      "episode_id": "6864df05b8a9f5c81761b4b5",
      "original_filename": "RSS_1500839292_podcast_1321_EP308 _ .json",
      "collection_name": "RSS_1500839292",
      "chunk_length": 208
    },
    {
      "chunk_text": "然後伯父就跑來林口嘛,那樹也變大顆一些。然後後來在林口住的習慣,小孩要出生想說買個房子,樹又再變得更大一顆,所以看著聖誕樹長大,好像說每年有一個記憶點在那邊。那其實我本來對聖誕節沒有什麼樣的感覺,就覺得這是一個交換禮物的季節。那後來呢,是觀察我岳母家的一個生態之後呢,開始發現這個節日它特別的地方。像在聖誕夜的時候呢,",
      "chunk_id": "1956045c-3d83-4a67-a668-20419c4ec323",
      "chunk_index": 6,
      "episode_id": "6864df05b8a9f5c81761b4b5",
      "original_filename": "RSS_1500839292_podcast_1321_EP308 _ .json",
      "collection_name": "RSS_1500839292",
      "chunk_length": 159
    },
    {
      "chunk_text": "有一個小椅子會在樹下面放熱牛奶,給聖誕老人喝的啦。台灣家庭我不確定大家會不會做,就算真的要做,老爸就開始講說那會長螞蟻,老媽就講說放一個牛奶在那邊有浪費,就大家會有一些意見這樣子。可是他們是很認真在經營聖誕節,就讓小朋友相信說真的有聖誕老人跟牙籤子的存在,他們認為這是很重要的東西。那我後來也開始想通這樣的東西,因為你還小的時候,我不知道大家有沒有試過,就是你會拿一個雨傘然後當成是降落傘沖,",
      "chunk_id": "4aeb120c-d899-426f-bc69-ea0869b69c20",
      "chunk_index": 7,
      "episode_id": "6864df05b8a9f5c81761b4b5",
      "original_filename": "RSS_1500839292_podcast_1321_EP308 _ .json",
      "collection_name": "RSS_1500839292",
      "chunk_length": 196
    },
    {
      "chunk_text": "可能桌子上跳下來,然後越爬越高,最後面從櫥櫃上跳下來,從二樓跳下來。小男生,我相信很多人跟我有一樣的體驗。那你真的覺得那個雨傘是你的降落傘,你會開始去做一些改裝跟改造。本來先拿一個小黏土,然後綁牙線和上面套一個小塑膠袋,做一個模擬的降落傘,後來變成他媽自己下去人肉測試嘛。那不然就是拿著小車子在窗簷上面跑的時候,你真的會覺得你在賽車。你老媽推薦你在降落傘,",
      "chunk_id": "65e976a7-cdc4-4ed6-8d58-539a978cf84a",
      "chunk_index": 8,
      "episode_id": "6864df05b8a9f5c81761b4b5",
      "original_filename": "RSS_1500839292_podcast_1321_EP308 _ .json",
      "collection_name": "RSS_1500839292",
      "chunk_length": 178
    },
    {
      "chunk_text": "然後坐那種車車,你真的覺得你自己在開賽車。就是小時候我們看到的世界是那樣子的。所以呢,如果讓小朋友可以活在一個真的是很夢幻的世界裡面,好像是一個很不錯的idea。他長大之後,他或許會記得。那如果記得的話,我覺得想起來都會覺得很開心。那我不確定是不是所有西方的家庭都這樣,但是我老婆家他們是很用心的在經營小朋友對於節日的一個幻想,就希望說他們可以活在這樣的一個想像裡面。",
      "chunk_id": "a4100832-147b-4a42-a9e0-d8f254a7abc6",
      "chunk_index": 9,
      "episode_id": "6864df05b8a9f5c81761b4b5",
      "original_filename": "RSS_1500839292_podcast_1321_EP308 _ .json",
      "collection_name": "RSS_1500839292",
      "chunk_length": 184
    },
    {
      "chunk_text": "那只是有時候還是會產生一些悲劇,像有一次我小舅子跟小姨子就哭著回家。那時候我也在歐洲,我老婆就問他說發生什麼事?我被同學笑,為什麼你被笑?因為我說,我的這個禮物是聖誕老人送我的,然後他們跟我說根本沒有聖誕老人。然後之後呢,就開始被恥笑一頓,然後他就開始哭了嘛。妹妹就開始說明說哥哥開始哭,哥哥就跟他們講說,我們每年都準備牛奶跟巧克力,然後每次我們起來的時候牛奶跟巧克力都不見了。",
      "chunk_id": "19ba865d-2891-4abe-8fd3-876e79da1588",
      "chunk_index": 10,
      "episode_id": "6864df05b8a9f5c81761b4b5",
      "original_filename": "RSS_1500839292_podcast_1321_EP308 _ .json",
      "collection_name": "RSS_1500839292",
      "chunk_length": 189
    },
    {
      "chunk_text": "就換成是禮物,所以就是聖誕老人他把牛奶跟巧克力吃掉,然後送我禮物,就開始說明。可是有些小朋友的個性你知道嗎,就是我們當然說小朋友都是天真無邪嘛,可是我們都長大過,就是你同學裡面一定有那種fucking deep shit,你知道嗎,就是媽的王八糕子,然後就會在那邊自己最聰明,就一直瘋狂的恥笑,你啊,那是你老婆啦,你這個豬啊什麼的,當然他們不是講台語,他可能就是,反正媽就講義大利話在那邊電他,然後電到他覺得自己很丟臉。",
      "chunk_id": "4e3ba733-15ac-4f6b-a3da-9f4fefc67283",
      "chunk_index": 11,
      "episode_id": "6864df05b8a9f5c81761b4b5",
      "original_filename": "RSS_1500839292_podcast_1321_EP308 _ .json",
      "collection_name": "RSS_1500839292",
      "chunk_length": 210
    },
    {
      "chunk_text": "然後回來對家人生氣,就說為什麼你們不跟我說聖誕老人是假的。可是我覺得最屌的地方是,即便小朋友被其他小朋友弄成這樣喔,那他們還是有辦法繞回來,讓他重新的相信聖誕節。雖然我覺得其實他們應該多少也知道,就是說自己的媽媽是希望讓你還是相信,可是其實我已經知道是假的,但是我也配合演出。就小朋友其實不笨啦,小孩不笨真的。那至少就是他還是願意配合,大家一起在一起,",
      "chunk_id": "ed9c4bc0-16a0-4dff-8b00-39868f218b60",
      "chunk_index": 12,
      "episode_id": "6864df05b8a9f5c81761b4b5",
      "original_filename": "RSS_1500839292_podcast_1321_EP308 _ .json",
      "collection_name": "RSS_1500839292",
      "chunk_length": 176
    },
    {
      "chunk_text": "在聖誕節,想像一下真的有聖誕老公公的存在之類的。我覺得那個是很特別的一個感受。那我自己在台灣開始對聖誕節產生一種嚮往的是,在兩年前我們換到一棵比較大棵的聖誕樹,然後開始很用心的雕琢它,這邊還是要稍微講一下,我從來不會去擺聖誕樹,收聖誕樹,或是掛吊飾跟慘燈,那全部都我老婆弄。但是呢,我還是很無恥的會去欣賞它,每次這個樹弄好,我就是坐在樹下欣賞這一棵樹,我覺得媽,聖誕樹真的太漂亮,太浪漫了。",
      "chunk_id": "72283b2e-46d3-4739-bbea-c8bc7ed0403a",
      "chunk_index": 13,
      "episode_id": "6864df05b8a9f5c81761b4b5",
      "original_filename": "RSS_1500839292_podcast_1321_EP308 _ .json",
      "collection_name": "RSS_1500839292",
      "chunk_length": 195
    },
    {
      "chunk_text": "所以我就會跟我老婆提說,可不可以我去拿,不是你拿,是我拿,所以我提早把它拿出來,然後我來擺好不好,我來慘燈,還是不行,就是我提出了我要去做服務,還是不行,她寧願自己弄,然後她就是一定要在11月底才把聖誕樹拿出來,然後再來另外一個讓我感到比較失望,就是她在12月底,就是差不多31號,1月1號,2號左右,她就會把樹給收起來,其實每次把樹收起來的時候,我覺得感受到一種",
      "chunk_id": "f8ae5cb6-a9b4-4293-9ab0-6f16623abf62",
      "chunk_index": 14,
      "episode_id": "6864df05b8a9f5c81761b4b5",
      "original_filename": "RSS_1500839292_podcast_1321_EP308 _ .json",
      "collection_name": "RSS_1500839292",
      "chunk_length": 182
    },
    {
      "chunk_text": "很難過的感覺,就酸酸的啦,雖然我也不會多說什麼,就坐在房間裡面看著她把樹弄起來,那就會希望說明年還可以趕快再過一次聖誕節,所以我覺得關鍵是有一個終點啊,就開始想通一些事情,你知道,東西要有終點,沒有終點的話就沒有那麼珍貴,因為你知道這東西一定會結束,早晚會結束,那有些東西甚至是你很明確知道它什麼時候會結束,因為你知道它會結束,所以它才變得很珍貴,你可能會覺得是幹話,但是我相信",
      "chunk_id": "759a316e-5f44-4550-8a86-b6cfd9a8469b",
      "chunk_index": 15,
      "episode_id": "6864df05b8a9f5c81761b4b5",
      "original_filename": "RSS_1500839292_podcast_1321_EP308 _ .json",
      "collection_name": "RSS_1500839292",
      "chunk_length": 189
    },
    {
      "chunk_text": "已經感受過或是還沒感受過的,就稍微照我的指示跟你說,就是你要開始去相信聖誕節的一些魔幻的力量,然後再來就是你要有這種季節性的儀式感,不要學他媽一堆小吃店什麼懶教餐廳,把那個樹擺出來擺一整年懶得收,一部分人是懶得收啊,一部分就想說樹都買了,擺在那邊很好看啊,就跟我想法一樣,我之前跟她講說樹可以擺一整年,然後被她罵,她就說你擺一整年聖誕節又不特別,之前不理解,後來就理解了,",
      "chunk_id": "2382aa8c-e8dd-4d6a-9b5d-1704fd2bf1ec",
      "chunk_index": 16,
      "episode_id": "6864df05b8a9f5c81761b4b5",
      "original_filename": "RSS_1500839292_podcast_1321_EP308 _ .json",
      "collection_name": "RSS_1500839292",
      "chunk_length": 186
    },
    {
      "chunk_text": "所以在那邊分享給大家,如何正確的過聖誕節,那我對於我自己小孩的養育,我覺得我也會讓他相信聖誕節是真的,然後會做一些橋段的設計,就是讓他真的認為說是聖誕老人把東西給他,我覺得這是一個很重要的東西,直到哪一天有一個同學跟他說聖誕老公公是假的,到他之前我都會希望讓他相信聖誕老公公是真的,好啦那祝大家聖誕快樂,那我昨天有跟我太太討論說明年要買什麼樣的股票,因為我還真的不知道明年要買什麼樣的東西,目前真的沒有特別,",
      "chunk_id": "e5fed573-53c6-4ca1-b006-70ac139e6ad7",
      "chunk_index": 17,
      "episode_id": "6864df05b8a9f5c81761b4b5",
      "original_filename": "RSS_1500839292_podcast_1321_EP308 _ .json",
      "collection_name": "RSS_1500839292",
      "chunk_length": 204
    },
    {
      "chunk_text": "這算是一個比較罕見的現象,過去的幾個修正,像是肺炎,貿易戰,四年前貿易戰,或是說像是七八年前的那時候中國的人民幣危機等等的,你大概都知道說你要買什麼東西,那可是這一波還真的不太知道明年可以買什麼,我現在手上自己在弄的東西就是原物料,中國解封的東西大概在兩三集前跟大家講說劉鶴他要去救房子了,所以這個可能可以弄一個短期的題材,",
      "chunk_id": "759bc602-769d-43e0-8fde-879044e23192",
      "chunk_index": 18,
      "episode_id": "6864df05b8a9f5c81761b4b5",
      "original_filename": "RSS_1500839292_podcast_1321_EP308 _ .json",
      "collection_name": "RSS_1500839292",
      "chunk_length": 162
    },
    {
      "chunk_text": "所以短期弄一弄是有機會的,所以各個什麼散裝啊,水泥鋼鐵什麼,大家應該都有看到他有動靜,那我這邊要跟大家講那個不是什麼長期投資,所以不要什麼回頭之後,然後跟我講說這個你還抱著嗎,這種東西我是不可能常抱的,這種就是我們那種短線仔玩一玩,抽插一下就走了,那明年還有看到什麼樣的機會呢,目前就是看到再生晶圓可能有些機會,3奈米的廠開始啟用之後,那個用量會放量,所以可能有機會,再生晶圓廠就中沙聖羊辦,",
      "chunk_id": "2d860f25-dca4-4d8b-8c8c-eaaf5372b724",
      "chunk_index": 19,
      "episode_id": "6864df05b8a9f5c81761b4b5",
      "original_filename": "RSS_1500839292_podcast_1321_EP308 _ .json",
      "collection_name": "RSS_1500839292",
      "chunk_length": 196
    },
    {
      "chunk_text": "可是中沙法說講的東西跟市場本來給他的預期是有落差的,所以大家開始懷疑說這東西到底有沒有,知道他會成長,可是到底有沒有像市場派人士想像的這麼好,那再來呢,可能有些人在看廣罩,為什麼看廣罩呢,他的故事是這樣,就是說TSM他的機台老舊,他們不想要再繼續去生產一些廣罩,所以把廣罩外爆出去,目前的客戶大多數都已經接受,當然還有一部分不接受,但是慢慢的,因為他們就是不要做,",
      "chunk_id": "43e83167-4eb9-47e9-851f-ef9abe22dd4f",
      "chunk_index": 20,
      "episode_id": "6864df05b8a9f5c81761b4b5",
      "original_filename": "RSS_1500839292_podcast_1321_EP308 _ .json",
      "collection_name": "RSS_1500839292",
      "chunk_length": 182
    },
    {
      "chunk_text": "那到底誰分得多,這個不確定,用事實上來看,可能日本跟美國的這兩家是比較大,台灣的比較小,可是有個說法就是說,台灣的淨水樓台現得約,所以可以分到比較多,這個就比較難去做判斷,那以估值來講,台灣的也是最貴的,所以可能就是有有心人在照顧之類的,不過這個題材是蠻明確的,就是說他們確實是有這樣",
      "chunk_id": "a6cbee40-7b5e-4f04-9316-b7b6366c0f83",
      "chunk_index": 21,
      "episode_id": "6864df05b8a9f5c81761b4b5",
      "original_filename": "RSS_1500839292_podcast_1321_EP308 _ .json",
      "collection_name": "RSS_1500839292",
      "chunk_length": 142
    },
    {
      "chunk_text": "做,只是你不確定說,誰可以吃到多少,然後再來就是現在的價格是不是已經反應完的,這個不確定,但這個也是少數在半導體裡面,就是會看到會成長的東西,不過他是屬於很次要的一個題材,就是這個Photomask,他並不是說半導體的一個主力題材,一般可以被稱為主力題材的東西,一定要很大的量,然後再來就是他要有相當程度的族群性,就是你只有少部分幾家公司有這樣的東西,比較難",
      "chunk_id": "ddc5807f-b568-4fc2-ac7d-9e6b74ea1cb8",
      "chunk_index": 22,
      "episode_id": "6864df05b8a9f5c81761b4b5",
      "original_filename": "RSS_1500839292_podcast_1321_EP308 _ .json",
      "collection_name": "RSS_1500839292",
      "chunk_length": 179
    },
    {
      "chunk_text": "在市場裡面做起來,可能會被少部分拿來當成是一個超過的標的,可是他無法帶動整個情緒,要帶動情緒要有比較大型的故事內容,消費性電子,手機,平板,PCMP,那不然就是伺服器,車用,這些都是量比較大的東西,VRAR也算是比較次要小的,跟衛星算同一個位階,那我們目前上述講的東西,在明年都沒有看到有什麼樣的契機,有些東西是會長多啦,",
      "chunk_id": "2997a412-7d75-47f8-857c-10e8cc2eb816",
      "chunk_index": 23,
      "episode_id": "6864df05b8a9f5c81761b4b5",
      "original_filename": "RSS_1500839292_podcast_1321_EP308 _ .json",
      "collection_name": "RSS_1500839292",
      "chunk_length": 161
    },
    {
      "chunk_text": "伺服器跟車用是長多沒有問題,只是在短期內我們找不到有刺激股價繼續往上的一些理由,現在真的是比較難找到一些這種,一般我們會希望在未來半年內能見度可以看到他營收的一郎一兒可能落在15到20%以上,那EPS會越開越好,這樣就是示威說他可能是有機會會被市場的資金關照,但目前其實未來的不確定性真的太高了,那天有朋友找我去吃飯,吃的是喜相逢,一個在台北市,",
      "chunk_id": "5dc9d883-193f-47f3-bd78-fcc76be8b1d1",
      "chunk_index": 24,
      "episode_id": "6864df05b8a9f5c81761b4b5",
      "original_filename": "RSS_1500839292_podcast_1321_EP308 _ .json",
      "collection_name": "RSS_1500839292",
      "chunk_length": 173
    },
    {
      "chunk_text": "不誇張,本來我是要去韓國的,就預計12月都要去韓國,那知道他們有定喜相逢,我就說那韓國可以晚一點去,因為這個餐廳太有名了,就是非常難訂,然後我看我的留言才知道說好像黃國昌在前幾天的YouTube上面有提到說這個餐廳就是要有一些人賣,然後有一些政商實力的人才訂得到什麼的,好像出作業給他的聽眾還殺小的,所以就一堆人跑來這邊留言說什麼,黃國昌出了作業你就拿去做達,",
      "chunk_id": "036dea59-8a78-410a-ba68-0ecfe916fa5b",
      "chunk_index": 25,
      "episode_id": "6864df05b8a9f5c81761b4b5",
      "original_filename": "RSS_1500839292_podcast_1321_EP308 _ .json",
      "collection_name": "RSS_1500839292",
      "chunk_length": 180
    },
    {
      "chunk_text": "那個不是我訂的啦,反正就是朋友照顧,叫我一起去我就一起去,還不錯吃啊,他本來訂請客樓,如果是訂請客樓,我就照我的正常行程跑去韓國了,然後當然訂這個喜相逢就來吃看看,是一個很優秀的台菜,老闆娘還是聽眾說有聽過,我覺得蠻意外的,幹他題外話,反正總之就是說在餐廳上面認識了谷乾爹,他是一個很優秀的YouTuber,反正大家先客套一下嘛,",
      "chunk_id": "e3d3fcb0-fd42-48cc-b662-488a2e4175b5",
      "chunk_index": 26,
      "episode_id": "6864df05b8a9f5c81761b4b5",
      "original_filename": "RSS_1500839292_podcast_1321_EP308 _ .json",
      "collection_name": "RSS_1500839292",
      "chunk_length": 165
    },
    {
      "chunk_text": "久仰久仰,之後就開始交換意見加個Line什麼的,阿上他是看比較空啦,其實谷乾爹的內容我覺得蠻屌的,就是說他是有打進投資交易的圈子裡面,就是我們平常會傳一些總經相關的資料,元大的一個首席,他總經相關的內容大家會看,然後再來就是之前艾謝克,艾謝克家的東西大家不太傳的,不是說他不行啦,就是說他就是比較樂觀的那一種,",
      "chunk_id": "e36646d6-5526-48f1-a35a-0838f9105cfa",
      "chunk_index": 27,
      "episode_id": "6864df05b8a9f5c81761b4b5",
      "original_filename": "RSS_1500839292_podcast_1321_EP308 _ .json",
      "collection_name": "RSS_1500839292",
      "chunk_length": 155
    },
    {
      "chunk_text": "大家放心裡都知道,你終究是要做多的,那最近就比較少看到有在傳艾謝克的內容,就比較常看到傳谷乾爹的,所以谷乾爹是一個後期之秀,非常厲害,那他的背景也是很強勁,那我們稍微討論一下,其實他做總經跟指數相關的,其實跟我們做個股的不謀而合,大家意見是差不多的,都覺得說明年他甚至有機會看到所謂的二度去庫存,那當然庫存就是庫存嘛,",
      "chunk_id": "6e8128de-3dbf-4f7b-95f8-0c5c4458d7a3",
      "chunk_index": 28,
      "episode_id": "6864df05b8a9f5c81761b4b5",
      "original_filename": "RSS_1500839292_podcast_1321_EP308 _ .json",
      "collection_name": "RSS_1500839292",
      "chunk_length": 159
    },
    {
      "chunk_text": "去庫存就是一個線性的動作嘛,為什麼把它稱為說是一個二度去庫存,意思就是說,我們現在講說第二季有可能庫存會壓回正常水位嘛,正常水位的論述依據是基於說,需求假設是按照均值的發展的話呢,那庫存降到這邊,大壓力就會變很小,價格可能就不會再下去了,庫存就不會再往上堆了,一切都沒有問題,但現在怕的是什麼,就是說,庫存降到那個位置,可是需求整個不見的話怎麼辦,",
      "chunk_id": "08472356-842d-4f8b-889e-3dc42f3a3f73",
      "chunk_index": 29,
      "episode_id": "6864df05b8a9f5c81761b4b5",
      "original_filename": "RSS_1500839292_podcast_1321_EP308 _ .json",
      "collection_name": "RSS_1500839292",
      "chunk_length": 174
    },
    {
      "chunk_text": "那我也不知道怎麼辦,要跑去問聯準會那幾個阿呆,就是他們前面通膨是暫時的,死都不升息,現在要生狂生,一些數據就下去了,繼續生,就是要生到死為止,美國很多企業家都開始出來哀號說這個政策有問題,照樣就是要把它生到底,所以聯準會我相信有在略有被檢討,就像大家都說不要跟聯準會作對嘛,他們其實就是蠻幹的一群人,所以我們不知道說這樣的利率會影響實體經濟到什麼樣的一個程度,",
      "chunk_id": "9a09e325-3f17-433f-864c-29ebfb4dab8c",
      "chunk_index": 30,
      "episode_id": "6864df05b8a9f5c81761b4b5",
      "original_filename": "RSS_1500839292_podcast_1321_EP308 _ .json",
      "collection_name": "RSS_1500839292",
      "chunk_length": 180
    },
    {
      "chunk_text": "情況就是二度去庫存,降到正常水位還不夠,因為需求不見了,價格整個變得更差,所以營收獲利會再進一步的往下調,那像這種是比較可怕的劇本,當然有些人就覺得這個劇本一定會發生,但我的看法是我覺得我還是要看到一些供應鏈的資料才可以做一些判斷,包含說之前的第二季,然後上一集提到說看到一些被動元件的資料,所以覺得有可能會第三季,都是我要看到資料才可以做判斷,我不喜歡用瞎猜的方式,",
      "chunk_id": "dccb78b0-13e5-454f-824e-11fac04d5d80",
      "chunk_index": 31,
      "episode_id": "6864df05b8a9f5c81761b4b5",
      "original_filename": "RSS_1500839292_podcast_1321_EP308 _ .json",
      "collection_name": "RSS_1500839292",
      "chunk_length": 184
    },
    {
      "chunk_text": "會有機會救到整體消費市場的消息,就是中國解封嘛,那中國解封目前看起來是還蠻順的,就是說正式的進入一個大感染潮,像是在富士康這邊,很多員工是確診嘛,那也有消息傳出說,他叫你乾脆不要驗了回去上班,就跟台灣很像啦,當時有些固執我相信應該也希望你們不要驗啦,反正直接來上班就好,因為疫苗都打完了,不然你要怎麼樣,那這種恐慌它是很可怕的,就是說在媒體長時間的洗腦之間,",
      "chunk_id": "673ba07a-2e71-451c-a592-9bedc80bc140",
      "chunk_index": 32,
      "episode_id": "6864df05b8a9f5c81761b4b5",
      "original_filename": "RSS_1500839292_podcast_1321_EP308 _ .json",
      "collection_name": "RSS_1500839292",
      "chunk_length": 179
    },
    {
      "chunk_text": "政府官員把這個當成是一個政績之下,就大家會覺得病毒真的很可怕,那我們瘋的越死,瘋的越好,就是越卓越的一個表現嘛,就其實我們跟歐美的思維是差很多的,那等到真的解封之後呢,就開始會呈現一種,啊你現在是不是雙標,前面說很可怕,那現在又叫大家不要怕,那你到底要我們怎麼樣,那像台灣後來是在日本開放之後呢,才正式的走出來,不知道大家還記不記得,因為很多人其實那個記憶力是很短暫的啦,就是我看他幾個月前PO文都在那邊講說很可怕,小孩子都不敢帶出去,然後現在要去日本玩,去哪玩,",
      "chunk_id": "85d2d263-08db-4e7a-84ac-be6a9980cb55",
      "chunk_index": 33,
      "episode_id": "6864df05b8a9f5c81761b4b5",
      "original_filename": "RSS_1500839292_podcast_1321_EP308 _ .json",
      "collection_name": "RSS_1500839292",
      "chunk_length": 232
    },
    {
      "chunk_text": "他都沒有在插小,可是其實是一樣的病毒株,其實是一樣的疫苗施打率,一樣的你打了兩劑三劑,大家的狀況都一樣的,但是因為日本開放,日本太香了,所以你想要出去玩,就再也不在意,現在每天確診有幾個,你去查,現在每天確診還是很高,死亡數量還是很高,可是就沒有人要屌啦,因為本來就不需要去在意這樣子的東西,就是你終究都要去面對,就是每個人都要感染一輪,然後這是這個病毒無可避免的一個結果,那現在中國就等於是在走一次台灣走過的路,那就我所知呢,中國的朋友分享,",
      "chunk_id": "da79ff89-1b41-4001-9648-e14481358934",
      "chunk_index": 34,
      "episode_id": "6864df05b8a9f5c81761b4b5",
      "original_filename": "RSS_1500839292_podcast_1321_EP308 _ .json",
      "collection_name": "RSS_1500839292",
      "chunk_length": 222
    },
    {
      "chunk_text": "在一些大城市下路上看不到太多人,因為全部人都躲在家裡,那有些是已經生病了,有些是還沒有生病,可是就很害怕,因為傳染速度真的太快了,然後現在他們有那種醫療卡住的一個狀況,一時間的爆炸,所以讓整個國內的防疫資源都變得非常的緊繃,那不過我也觀察到中國這邊的股票呢,其實跟台灣或是說像台灣跟前面先解封的國家那個節奏都差不多,解封的瞬間就先炒一下什麼口罩,醫療什麼都沒有的嘛,然後再來就是炒國內的旅遊機票,",
      "chunk_id": "828c00bd-1284-49cb-9fe6-a1e5d8520363",
      "chunk_index": 35,
      "episode_id": "6864df05b8a9f5c81761b4b5",
      "original_filename": "RSS_1500839292_podcast_1321_EP308 _ .json",
      "collection_name": "RSS_1500839292",
      "chunk_length": 198
    },
    {
      "chunk_text": "或是各種航空、海運相關的東西,很多都會起來一波,但是這個應該都是短題材,就是它之後會下去啦,那我們要觀察的就是說,在中國人大量的染疫康復之後呢,那他們到底還有沒有消費力,目前市場上的主要論述是認為應該是沒有消費力,我自己是站在這一塊啦,就是我覺得應該是沒有錢了,因為真的封太久了,如果說你是在今年中以前解封,可能狀況會不一樣,但是你已經封到年底,",
      "chunk_id": "b0902fa7-3f7e-40c1-a13c-3e3d05fc0b5d",
      "chunk_index": 36,
      "episode_id": "6864df05b8a9f5c81761b4b5",
      "original_filename": "RSS_1500839292_podcast_1321_EP308 _ .json",
      "collection_name": "RSS_1500839292",
      "chunk_length": 173
    },
    {
      "chunk_text": "其實蠻多人現在應該是在一個很緊急的狀態,像他們一些小區一封是封幾個月的,房租還是要繳,生活費還是要繳,車貸也是要繳,大家都沒錢啦,所以終於可以回到正常的工作,趕快看有沒有辦法把經濟拉回來一些,可是你說這些人出來會報復性消費,我相信現在應該是沒有人買單這個劇本,這個劇本是在年中以前,蠻多人在討論說中國解封會有報復性的消費,當時有跟大家分享這樣的一個論點,但因為你看狀況就是會改變嘛,所以預測有時候沒有太多意義,",
      "chunk_id": "0c9d838e-e262-4061-beac-816b658abeeb",
      "chunk_index": 37,
      "episode_id": "6864df05b8a9f5c81761b4b5",
      "original_filename": "RSS_1500839292_podcast_1321_EP308 _ .json",
      "collection_name": "RSS_1500839292",
      "chunk_length": 205
    },
    {
      "chunk_text": "因為你根本不知道未來會怎麼樣發展,你只能夠在事情發生之後去做一個未來的投射,所以既然現在才解封,那我們對未來的投射就是說,幹沒錢了啦,老鐵要打工,要上班,要上工了,又沒有錢出來消費,所以可能短時間內不會看到消費的刺激,但是有一個潛在的可能性,就是我們還是要盡量在一些死灰裡面找一些可能的機會,那就是說中國的政府如果有大量的補貼,像之前補貼車子那樣子,或是說現在",
      "chunk_id": "ae0bd282-79a8-411d-8ef6-aa92580c2b39",
      "chunk_index": 38,
      "episode_id": "6864df05b8a9f5c81761b4b5",
      "original_filename": "RSS_1500839292_podcast_1321_EP308 _ .json",
      "collection_name": "RSS_1500839292",
      "chunk_length": 180
    },
    {
      "chunk_text": "東南海的一線城市有蠻多在補貼消費電子,大量的補貼降準,放出流動性,有可能還有機會幫忙拉一波啦,所以接下來可能就看中國這邊有沒有機會帶動一下消費這樣子,因為我們在歐美應該是比較難看到這樣子的狀況,現在利率升到那個條件,很多人的房價跌,車價跌,那個手頭應該是更緊的啦,本來那個儲蓄率是蠻高,現在都壓到很低了,所以我個人是認為說,可能要期待一下看中國這邊有沒有什麼樣的變化,那講完了整個前情提要之後,反正就是跟大家表示說,",
      "chunk_id": "0966e631-241e-4a81-a5ae-a6d98dfd2000",
      "chunk_index": 39,
      "episode_id": "6864df05b8a9f5c81761b4b5",
      "original_filename": "RSS_1500839292_podcast_1321_EP308 _ .json",
      "collection_name": "RSS_1500839292",
      "chunk_length": 208
    },
    {
      "chunk_text": "我覺得未來短期內我們看不到那種像之前那種中長線的題材,當然有一些大的故事還在擺在那邊,AI資料中心都還在那,只是因為我們找不到在未來的幾個月可以持續看到漂亮year on year的東西,所以就變成不知道挑什麼標題問我老婆嘛,那她就跟我講了幾口,這邊跟大家分享,這是我老婆的選股,所以我自己是弄了一個戶頭給她,那就會照她的指示,拿一千萬就買下去這樣子,有些東西可能比較難買到,但會想辦法可能透過IB或是說一些富維托啊什麼的,",
      "chunk_id": "dbc21889-2015-4bc1-b1b4-4fa1f21fce93",
      "chunk_index": 40,
      "episode_id": "6864df05b8a9f5c81761b4b5",
      "original_filename": "RSS_1500839292_podcast_1321_EP308 _ .json",
      "collection_name": "RSS_1500839292",
      "chunk_length": 212
    },
    {
      "chunk_text": "反正就是把她想要的標的買一包,然後看說她的績效怎麼樣,那如果兩年之後她的績效真的比我好的話,以後我連股票都不要做了,我每次開節目就跟大家聊天講電玩的東西,那股票給我老婆去抄就好,我是一個很現實的人,就是我覺得你做得好,你行你上,就是我們在不管婚姻還是朋友關係,很重要一點就是機會成本,當有一個東西是有誰做得很好,他又可以花比較少的時間達到卓越的成效,就給他做就對了,大家都要找到一個適合的位置,",
      "chunk_id": "87ae890e-4ca0-4e97-978f-a00e33068d55",
      "chunk_index": 41,
      "episode_id": "6864df05b8a9f5c81761b4b5",
      "original_filename": "RSS_1500839292_podcast_1321_EP308 _ .json",
      "collection_name": "RSS_1500839292",
      "chunk_length": 197
    },
    {
      "chunk_text": "那我老婆選的股票我覺得還蠻有趣的,稍微跟大家分享一下,第一個她挑家樂福,家樂福可能要在歐股買,然後第二個好勢多,好勢多之前有買過,但是我被洗掉,因為這不是我自己真的非常熟悉的東西,雖然說我們很常逛好勢多,我也知道好勢多的模式,他主要是以會員卡作為一個最大的獲利來源,不過意思就是說,因為他不是一個你真的很熱衷很喜歡的東西,所以你可能對他的持有的信仰就不會這麼高,所以抱不太住,",
      "chunk_id": "1ee1e2ac-b9c8-49ad-a5de-ee7649184ef1",
      "chunk_index": 42,
      "episode_id": "6864df05b8a9f5c81761b4b5",
      "original_filename": "RSS_1500839292_podcast_1321_EP308 _ .json",
      "collection_name": "RSS_1500839292",
      "chunk_length": 188
    },
    {
      "chunk_text": "他今天不太會動的時候就想說他真的好無聊把他賣掉,結果我一賣完就開始狂噴,這應該是兩年前的節目那時候有講到這一段,就是把他賣掉的時候就狂噴,他覺得好勢多是一個很好的公司,然後再來富邦美,為什麼會挑富邦美呢,他認為Momo會統一整個電商,他說在Momo上面消費,這全部都是他講的,所以我就稍微轉述一下,我也沒有去做考證,因為我們家的消費都是我老婆在處理,他說Momo上面買東西,信用卡都不用去輸入認證碼,",
      "chunk_id": "41f0a3a4-5d01-4378-a3f3-2c12445433dc",
      "chunk_index": 43,
      "episode_id": "6864df05b8a9f5c81761b4b5",
      "original_filename": "RSS_1500839292_podcast_1321_EP308 _ .json",
      "collection_name": "RSS_1500839292",
      "chunk_length": 200
    },
    {
      "chunk_text": "他經過一大堆平台,就一大堆都是信用卡要輸入,電話寄過來的密碼,什麼6碼或4碼之類的,然後再來就是有很多東西要跟你確認,那Momo就是你直接點了就買,其實我覺得跟PC Home也很像,PC Home其實我記得也是這樣子,就是24小時服務那邊其實是很快的,你東西只要點,然後就上去了,所以之前我在那邊買茶或什麼的,那像我老婆蠻多都是使用Momo在買,然後再來就是他覺得Momo上面什麼死人骨頭都買得到,狗的東西,小孩的東西,我們家用的商品,或是吃的喝的東西,",
      "chunk_id": "d7affed7-5ce2-412e-b86f-0342691546bf",
      "chunk_index": 44,
      "episode_id": "6864df05b8a9f5c81761b4b5",
      "original_filename": "RSS_1500839292_podcast_1321_EP308 _ .json",
      "collection_name": "RSS_1500839292",
      "chunk_length": 227
    },
    {
      "chunk_text": "我自己每次囤在家裡的什麼可樂茶水什麼的,他說價格都很漂亮,然後再來就是量也很齊,以及種類反多,所以他認為Momo會統一江山,這個是他大量的在網路消費之後的一個心得,所以他認為富邦每日可以買這家公司,那再來Coco可樂,這不要說了,這是我們兩個最愛喝的飲料,保雅,保雅其實他來台灣就跟我講說這個東西會沉,他剛來就跟我講這件事,當時我沒有買,就蠻後悔的,",
      "chunk_id": "b6fc458f-d72a-445c-b215-0f7c17461502",
      "chunk_index": 45,
      "episode_id": "6864df05b8a9f5c81761b4b5",
      "original_filename": "RSS_1500839292_podcast_1321_EP308 _ .json",
      "collection_name": "RSS_1500839292",
      "chunk_length": 175
    },
    {
      "chunk_text": "大樹要有菊,他都跟我講說這個會沉,就是我們在逛的時候,他就會開始有很多的讚美,他們的東西很豐富啊,那架上各式各樣的東西都有,而且進去一輪可以逛很久,以前我不懂,就是我從來沒有進去過保雅,那你進去保雅就可能買個什麼牙線之類的,反正就把它當成是那種一分利百貨,有的沒有的,那種比較基礎的日常用品,之前我是這樣想像他,後來才知道說裡面其實有很多東西,那保雅大樹他都覺得非常的有機會,",
      "chunk_id": "31bb4313-f8ca-4f6f-8239-2ba51437fe20",
      "chunk_index": 46,
      "episode_id": "6864df05b8a9f5c81761b4b5",
      "original_filename": "RSS_1500839292_podcast_1321_EP308 _ .json",
      "collection_name": "RSS_1500839292",
      "chunk_length": 188
    },
    {
      "chunk_text": "當然大樹現在已經整個都炒過一輪了嘛,那保雅也算是前面有走過一波這樣子,不過呢他認為還是很有機會,那我問他,我說你總是要看到一個企業的未來展望啊,不能只是說什麼現在很好就沒問題,他說這個店如果可以越開越多,然後跑去China跑去哪裡開應該都很有機會,這是他的心得,所以他認為保雅還是可以看的,那再來呢Yunicolo,這時候我就問他說為什麼不要買Zara,雖然Zara我不確定買不買得到,Yunicolo是買得到,他就跟我講說Yunicolo還是比Zara好一些,這是他的意見,",
      "chunk_id": "900db88d-1644-4980-85b9-5cc0a78a15f2",
      "chunk_index": 47,
      "episode_id": "6864df05b8a9f5c81761b4b5",
      "original_filename": "RSS_1500839292_podcast_1321_EP308 _ .json",
      "collection_name": "RSS_1500839292",
      "chunk_length": 238
    },
    {
      "chunk_text": "然後最後面的McDonald,就是我們天天在吃的麥當勞,真的超常在吃的,所以看下來每個都是很生活化的選股,其實這樣的一個選股方式,老實講也真的蠻適合大家的,就是有些人不知道怎麼入門投資,可是又想要去試看看那種主動挑股票的感覺,不妨可以嘗試不要去挑一些媒體或是網路上的那種大名,就是可能大家會跟你講說蘋果嘛,特斯拉嘛,微軟什麼的,你其實可以試看看從生活切入啦,就是我老婆這種選股模式,我們身邊有朋友是這樣子做,",
      "chunk_id": "41d6ef3c-bbcf-4dd8-aff8-8cc33b389484",
      "chunk_index": 48,
      "episode_id": "6864df05b8a9f5c81761b4b5",
      "original_filename": "RSS_1500839292_podcast_1321_EP308 _ .json",
      "collection_name": "RSS_1500839292",
      "chunk_length": 204
    },
    {
      "chunk_text": "就是我們剛剛前面講的那種網路大公司,雖然大家都在聊,可是你可能對他其實是不了解的,",
      "chunk_id": "fdbc9a70-d494-403d-961e-589ed6a628e8",
      "chunk_index": 49,
      "episode_id": "6864df05b8a9f5c81761b4b5",
      "original_filename": "RSS_1500839292_podcast_1321_EP308 _ .json",
      "collection_name": "RSS_1500839292",
      "chunk_length": 41
    },
    {
      "chunk_text": "那我覺得他這個選股會有機會的主要原因是因為現在市場上已經開始從本來那種成長股的邏輯變成價值股的邏輯,你有看到這樣的一個趨勢啊,那當然不是說價值股可以像成長股那樣子飆,只是如果在未來的一年內,我們是看不到科技股的一些強烈的動機的話,就只到可能兩三年後開始復甦之後,那是另外一回事嘛,那這段期間內有什麼東西是還會繼續成長,然後不太受通訊,",
      "chunk_id": "281aec93-9fe1-46b4-82e1-3b0541f456f8",
      "chunk_index": 50,
      "episode_id": "6864df05b8a9f5c81761b4b5",
      "original_filename": "RSS_1500839292_podcast_1321_EP308 _ .json",
      "collection_name": "RSS_1500839292",
      "chunk_length": 167
    },
    {
      "chunk_text": "通膨影響的,其實這些東西都是,就是他其實不太受通膨的衝擊啊,賣場如果說庫存很高,像美國的那幾個,前面搬爛掉,那是庫存頂到天上去嘛,可是現在很多其實都降下來了,那他們其實應該也是比較容易把通膨的壓力轉給消費者的一群,但他們之間會互相競爭啊,可是就是說他們可能蠻多是在賺類似一個中介的費用嘛,東西不是要生產的啊,人家把東西放到這,跟著調一些價格,是可以轉價給消費者的,所以可能這些東西會有機會",
      "chunk_id": "79883554-6f84-48ee-bf34-d833a041358a",
      "chunk_index": 51,
      "episode_id": "6864df05b8a9f5c81761b4b5",
      "original_filename": "RSS_1500839292_podcast_1321_EP308 _ .json",
      "collection_name": "RSS_1500839292",
      "chunk_length": 194
    },
    {
      "chunk_text": "那網購可能是你平常都還是會繼續使用,那大型的快時尚品牌呢,衣服總是要繼續穿的吧,而且他本來就是平價服飾,麥當勞更不要提,你不會因為說什麼外面有通膨你就不吃麥當勞了吧,而且麥當勞本來就算是一個廉價美食啦,然後在各地我認為他都是一個廉價美食,就是你可以用一個相對普適的價格吃到一個標準很高的東西,他們對於油,對於什麼薯條炸完幾分鐘之間要丟掉,這樣的標準都是設的非常嚴格的,所以這些東西可能真的可以",
      "chunk_id": "967e5c7b-f51d-45a9-860c-d056a8645c4c",
      "chunk_index": 52,
      "episode_id": "6864df05b8a9f5c81761b4b5",
      "original_filename": "RSS_1500839292_podcast_1321_EP308 _ .json",
      "collection_name": "RSS_1500839292",
      "chunk_length": 196
    },
    {
      "chunk_text": "做這一種,現在大家覺得外面通膨很可怕,那可能一些消費電子的需求會整個不見的狀況之下呢,那我們可能可以調這樣的一些東西,所以我自己會以這個作為一個基底,就我老婆買這些股票嘛,那我自己應該會以它為基底再去延伸看看有什麼其他的東西可以看,那就看一下這一波到底是不是在坊間講了好幾年的價值股復闢,就是價值股跟成長股之間的那個估值spread是越拉越大,大家都喜歡去堆那一些可能看起來",
      "chunk_id": "5f6cb027-42ec-4684-bd79-ad1f5abf1e05",
      "chunk_index": 53,
      "episode_id": "6864df05b8a9f5c81761b4b5",
      "original_filename": "RSS_1500839292_podcast_1321_EP308 _ .json",
      "collection_name": "RSS_1500839292",
      "chunk_length": 187
    },
    {
      "chunk_text": "d ratio是比較高的東西,他可能在未來的獲利展望上呢衝的比較快,可是也比較容易受到整個大環境的利率影響的一個股票,但是那些比較穩健的,那可以長年都穩定賺到獲利的公司,既然市場之中呢資金是比較不輕賴的,那一直有一個說法就是說有時候還有一堆資金也會回到這些股票上面,因為他們長期被低估,那我們就接著來持續看下去吧,好,那這集我們先聊到這邊,我們接下來進入QA的部分",
      "chunk_id": "2c723f98-20de-4034-a5d7-f26fcbb4a7ee",
      "chunk_index": 54,
      "episode_id": "6864df05b8a9f5c81761b4b5",
      "original_filename": "RSS_1500839292_podcast_1321_EP308 _ .json",
      "collection_name": "RSS_1500839292",
      "chunk_length": 182
    },
    {
      "chunk_text": "好,感謝這位阿中,也祝你們兩位早點有個三寶,就可以試看看在產台上面聽股癌",
      "chunk_id": "d32189e9-6ca0-46fa-86f4-7093f0c956a1",
      "chunk_index": 55,
      "episode_id": "6864df05b8a9f5c81761b4b5",
      "original_filename": "RSS_1500839292_podcast_1321_EP308 _ .json",
      "collection_name": "RSS_1500839292",
      "chunk_length": 36
    },
    {
      "chunk_text": "震撼耶,不知道各位老公有沒有跟老婆進去生產,聽說前陣子他有不讓大家進去,因為肺炎的關係嘛,那我那時候也是肺炎啦,只是他有讓我進去,就是說你要去遵循一些消毒的procedure什麼的,那做完之後呢,我只能夠說我比我老婆還緊張啦,其實我本來一直擔心說我老婆會chicken out你知道嗎,因為他是一個非常怕痛的人,所以我有做好心理準備,而且我老婆有跟我講這件事情,就是說當他chicken out,就是他突然不想生不敢生,想要把小孩收回去的時候呢,我要跟醫生講,",
      "chunk_id": "bdf55b56-f4c4-4053-9642-822f2d10597c",
      "chunk_index": 56,
      "episode_id": "6864df05b8a9f5c81761b4b5",
      "original_filename": "RSS_1500839292_podcast_1321_EP308 _ .json",
      "collection_name": "RSS_1500839292",
      "chunk_length": 230
    },
    {
      "chunk_text": "直接轉剖腹,因為我老婆她是一個會有panic attack的人,就如果說她真的很緊張很害怕的時候,那個會整個螺旋下去會變得一發不可收拾,所以我要直接跟她講說趕快把這個女人給我弄昏了,我們直接剖腹把小孩拿出來,但我很意外的是她很堅強的把小孩生出來,而且我們家的小孩呢,幹,頭很大,是大到那一種,你在月子中心住,醫生來尋訪的時候,不同的醫師進來,看到我兒子的頭,這個媽媽很辛苦喔,",
      "chunk_id": "71c9e47d-a4eb-4c36-9025-c3259c535842",
      "chunk_index": 57,
      "episode_id": "6864df05b8a9f5c81761b4b5",
      "original_filename": "RSS_1500839292_podcast_1321_EP308 _ .json",
      "collection_name": "RSS_1500839292",
      "chunk_length": 188
    },
    {
      "chunk_text": "在產房裡面看到的那個現象是很驚人的,就是小孩真的是噴出來,噴出來那個畫面你會覺得靠北喔,因為他頭很大,所以要裝一個吸盤,要把他吸出來,他出來的時候,他頭長得超好笑的,很像獨角獸,就多一個角,我想說幹完蛋了,有一個畸形的兒子,因為那個頭的凸出來的部分真的太大一顆了,不是說怎麼被棒球砸到一個包這樣,",
      "chunk_id": "2f330bd5-cda5-467a-8520-77cf998d6476",
      "chunk_index": 58,
      "episode_id": "6864df05b8a9f5c81761b4b5",
      "original_filename": "RSS_1500839292_podcast_1321_EP308 _ .json",
      "collection_name": "RSS_1500839292",
      "chunk_length": 148
    },
    {
      "chunk_text": "整個頭變得像埃及人那種,頭很長,然後伸出來,然後醫生跟我講說,那個沒關係,那個是吸盤吸,吸血變這樣,他一段時間就會恢復原狀,還要有恢復原狀,那那個畫面是真的蠻震撼的,就是說看到小朋友出來,檢查他的手指,檢查他的腳趾什麼的,那時候你的眼中就只看得到這個小孩子,老婆躺在那邊喘,暫時沒有任何精力看他,就在看這個小孩子,但後來我馬上就把注意力回到老婆身上,那她叫我減期待,她說你要不要減,我當然說好,減完期待之後呢,大概一段時間不敢吃小飯,",
      "chunk_id": "b9be7946-faf5-425d-b2df-32b2bb2f9694",
      "chunk_index": 59,
      "episode_id": "6864df05b8a9f5c81761b4b5",
      "original_filename": "RSS_1500839292_podcast_1321_EP308 _ .json",
      "collection_name": "RSS_1500839292",
      "chunk_length": 217
    },
    {
      "chunk_text": "那請問胡瓜是什麼味,下面一味,",
      "chunk_id": "d169b7c8-19d7-4a5e-802e-f3c44cf10012",
      "chunk_index": 60,
      "episode_id": "6864df05b8a9f5c81761b4b5",
      "original_filename": "RSS_1500839292_podcast_1321_EP308 _ .json",
      "collection_name": "RSS_1500839292",
      "chunk_length": 15
    },
    {
      "chunk_text": "下面一味,下面一味,下面一味,下面一味,",
      "chunk_id": "4f89ea3d-0401-449f-b4a8-36ff5ea13a71",
      "chunk_index": 61,
      "episode_id": "6864df05b8a9f5c81761b4b5",
      "original_filename": "RSS_1500839292_podcast_1321_EP308 _ .json",
      "collection_name": "RSS_1500839292",
      "chunk_length": 20
    },
    {
      "chunk_text": "你不可能吃完整個魚嘛,所以一般我們會講說,我們就吃魚裡面想要吃的部分,然後魚尾留給別人,於是網路上又出現一個梗圖,就是魚尾每次都超大一塊的,你想說魚頭魚身我都吃到了,魚尾就小小的留給別人,就魚尾是什麼翻倍之類的,那沒有辦法,這一定會遇到啦,簡單來講就是說,你越了解的東西,基本面越熟悉的,越有可能吃到診斷,但凡事都是有個兩面,你越容易吃到診斷,你了解很深的標準,",
      "chunk_id": "fc8aaca1-9f9c-4a98-acc2-58b88d20f31f",
      "chunk_index": 62,
      "episode_id": "6864df05b8a9f5c81761b4b5",
      "original_filename": "RSS_1500839292_podcast_1321_EP308 _ .json",
      "collection_name": "RSS_1500839292",
      "chunk_length": 181
    },
    {
      "chunk_text": "標的往往也是傷你最深的,跟他媽真愛一樣,那種你用心用最深的,要嘛是很快樂的結局,要嘛就是很慘的,幾乎找不到中間值,基本面派的朋友,蠻常就是那種爆賺,偶爾大賠,所以都要用資金控管來鎖,就一個部位可能買到10%20%上限,就不能再買了,因為他對於這個標的太熟悉了,所以會出事情,像這種故事真的是層出不窮啦,就是那種研究到很深,甚至為了一隻標的去組一個讀書會的,每次死掉都是這種,他媽死到整個,",
      "chunk_id": "99692ff4-a77c-4a01-beb4-44a9703328a6",
      "chunk_index": 63,
      "episode_id": "6864df05b8a9f5c81761b4b5",
      "original_filename": "RSS_1500839292_podcast_1321_EP308 _ .json",
      "collection_name": "RSS_1500839292",
      "chunk_length": 194
    },
    {
      "chunk_text": "其實大家真的賠到歪掉,因為太有信仰了,所以我們講說不要跟股票談戀愛,就在講這樣的事情啦,但是如果說你沒有談戀愛,你也很難抱得很長,你沒有那種信仰,你也很難去吃到翻倍再翻倍這樣子,就類似說我輝達是買了第五年了嘛,如果說前面都有因為一些回落就被洗掉的話,就不會有現在這樣的一個成果,那今年其實最低的時候,也有殺到我五年的成本,你可以想像嗎,你在五年持續一直投入喔,結果殺回你五年的成本,",
      "chunk_id": "f2e080fa-dd86-4ce5-9552-c6a6197fdb91",
      "chunk_index": 64,
      "episode_id": "6864df05b8a9f5c81761b4b5",
      "original_filename": "RSS_1500839292_podcast_1321_EP308 _ .json",
      "collection_name": "RSS_1500839292",
      "chunk_length": 191
    },
    {
      "chunk_text": "就會有一些壓力的產生啦,所以你如果想要賺整條的話,就是用不會控管的方式,10%資金丟進去就不要管他,你就把他想像成說你買了一個生意,那你不可以在短期內把他出掉,那你看好他未來幾年,那你怎麼會只報兩個禮拜對吧,那這是一個方法啦,那如果說還是要去用一些技術面的方式去鎖,或形態的方式去抓一些停利的話呢,是不太可能吃到整條餘頓,這個就是有好有壞啦,你用形態跟技術面做出場點的,你也比較不會有那種很大的回落啦,好下面會這個,",
      "chunk_id": "75ab8135-03a6-45e2-9e3a-56e192e83c4c",
      "chunk_index": 65,
      "episode_id": "6864df05b8a9f5c81761b4b5",
      "original_filename": "RSS_1500839292_podcast_1321_EP308 _ .json",
      "collection_name": "RSS_1500839292",
      "chunk_length": 208
    },
    {
      "chunk_text": "然後他講的這個,我稍微跟不知道的聽眾講一下,反正我有創Telegram嘛,美股台股跟一個加密貨幣嘛,就是讓大家",
      "chunk_id": "13f4625d-2de1-4495-8f94-a39f636a203c",
      "chunk_index": 66,
      "episode_id": "6864df05b8a9f5c81761b4b5",
      "original_filename": "RSS_1500839292_podcast_1321_EP308 _ .json",
      "collection_name": "RSS_1500839292",
      "chunk_length": 55
    },
    {
      "chunk_text": "可以在各自群組的主題下面做討論,那只是他們很多討論到後來就變成是私約出來,他們可能創一個什麼台北群、雙北群、桃園群、台中台南群什麼的,然後就私下變朋友,那這樣的朋友也是蠻志同道合啦,就是大家一定都是很喜歡輸錢,才會一起在股票市場裡面待著嘛,所以這樣的朋友可能還蠻不錯的,我覺得就是類似說你找到一個球友的感覺,那也祝大家都順利,下面會這個Grace Chan小白,她說這週三那集看不到,",
      "chunk_id": "99646ae2-d3b1-4125-971e-4160164e214b",
      "chunk_index": 67,
      "episode_id": "6864df05b8a9f5c81761b4b5",
      "original_filename": "RSS_1500839292_podcast_1321_EP308 _ .json",
      "collection_name": "RSS_1500839292",
      "chunk_length": 192
    },
    {
      "chunk_text": "好謝謝你的回報,那這個有蠻多聽眾都跟我講,那其實我現在老實講,我真的不太確定是我的hosting sound down的問題還是Apple的問題,我都分別寫信了,那sound down說是Apple的問題,Apple還沒有回覆我,那我有注意到這個現象,就是我的節目很常會不見,不是只有這個306、307不見,像是整個節目的本體之前也不見過兩次,反正就整個不見就對了,那我稍微問一下別人有沒有這樣的災情,好像沒有,就是我最常出現這樣的災情,我節目總共已經不見了五六次以上了,",
      "chunk_id": "9d32dbff-f443-4258-bc7c-a0229e48d9a4",
      "chunk_index": 68,
      "episode_id": "6864df05b8a9f5c81761b4b5",
      "original_filename": "RSS_1500839292_podcast_1321_EP308 _ .json",
      "collection_name": "RSS_1500839292",
      "chunk_length": 236
    },
    {
      "chunk_text": "我再想辦法解決它,那下次如果有發現再跟我講,因為我好像可以透過刷新的方式讓它跑出來,只是可能一段時間又會不見,我不知道它到底發生什麼事情,好下面會這個,想離職考機師的上班族,她說連續三集嘗試破解留言密碼,",
      "chunk_id": "feb7bf8e-4927-4bc7-bda5-cc33d1650995",
      "chunk_index": 69,
      "episode_id": "6864df05b8a9f5c81761b4b5",
      "original_filename": "RSS_1500839292_podcast_1321_EP308 _ .json",
      "collection_name": "RSS_1500839292",
      "chunk_length": 102
    },
    {
      "chunk_text": "好下面的東西我先跳過,然後我就直接來回覆她,她下面講說,待會再回去找看290是什麼,好那機師這個不要去補習,雖然我講這可能會斷一些人的財路,但是我們那時候在培訓的時候,裡面的教官都會這樣講,就說很多是去補習班的,那當然補習班它是可以讓你加強一些學科、數科考試,因為它知道會考什麼,那只是可能你在面試的回答上,",
      "chunk_id": "0f0df74f-6bf4-48d9-b406-87dd447ce4d6",
      "chunk_index": 70,
      "episode_id": "6864df05b8a9f5c81761b4b5",
      "original_filename": "RSS_1500839292_podcast_1321_EP308 _ .json",
      "collection_name": "RSS_1500839292",
      "chunk_length": 154
    },
    {
      "chunk_text": "會比較千篇一律,所以應該這樣說,就算你要去補習,你可能還是要自己做一些比較原創的東西,不然人家如果知道你是補習債,有時候會故意不用你,這是實際上在業內的一個狀況,那再來就是稍微準備一下國中、高中的物理,物理可能到高一程度就好了,就其它是不難的東西,像我自己是數學跟物理都不太好,就是我以前是不太念書的小朋友,可是像我去考這個都沒有問題,就是蠻容易的,我覺得那其實是比較像考你的邏輯跟判斷,它不是真的在考一些很複雜的東西,什麼三角函數,",
      "chunk_id": "0df9c3f1-f8ba-47f6-9175-fdc75a615f55",
      "chunk_index": 71,
      "episode_id": "6864df05b8a9f5c81761b4b5",
      "original_filename": "RSS_1500839292_podcast_1321_EP308 _ .json",
      "collection_name": "RSS_1500839292",
      "chunk_length": 217
    },
    {
      "chunk_text": "它其實那種東西蠻多是反射你就會直接有答案的,像是它可能畫了好幾條線,這樣曲折來曲折去,然後問你說左轉幾次、右轉幾次,那像這個我一秒鐘就可以知道說左轉幾次、右轉幾次,我覺得大多數人應該辦得到,可是你就可以看到在作答的時候,有些人在考卷上這樣翻來翻去,因為他好像沒有辦法直接從現在的正的角度直接看是幾個,他必須要翻來翻去來知道這個東西左彎幾次、右彎幾次,然後就被考官制止說你不可以這樣子,那再來就是考什麼,因為有三家都有報,",
      "chunk_id": "3eec3e30-ca97-4eab-a49e-1eae482fb9c8",
      "chunk_index": 72,
      "episode_id": "6864df05b8a9f5c81761b4b5",
      "original_filename": "RSS_1500839292_podcast_1321_EP308 _ .json",
      "collection_name": "RSS_1500839292",
      "chunk_length": 210
    },
    {
      "chunk_text": "一些反應測試,那手眼協調,還有多工測試什麼的,我覺得這些東西都比較偏向是先天的東西,那你有打電玩,我相信會有很大的幫助,因為電玩我們可能長時間就需要多工,不然說老婆那邊叫你不要打電動,那也是多工的一環,還要跟他吵架,然後同時玩電動,那一些快捷鍵或什麼的,我覺得打電動真的幫助很大,那學科的部分其實真的還好,學科部分可能就國中的物理稍微複習一下,就沒有什麼太大的問題了,",
      "chunk_id": "5e4e68d4-8d95-4674-ab75-8b0fa3123e20",
      "chunk_index": 73,
      "episode_id": "6864df05b8a9f5c81761b4b5",
      "original_filename": "RSS_1500839292_podcast_1321_EP308 _ .json",
      "collection_name": "RSS_1500839292",
      "chunk_length": 184
    },
    {
      "chunk_text": "上週呢,受訓會念很多書,就是我在受訓的階段念的書,可能是我高中加大學的總和吧,不誇張,那蠻多是原文的內容,所以英文差基本上一定進不去啦,英文的條件是還蠻嚴苛的,口語的能力呢,可能跟教官在飛行訓練的時候,有些外籍的講度的時候,你自己也會慢慢的變強,那飛行本身我覺得也是蠻吃天份的,就是有些人,因為我們那時候是兩家航空公司一起在那邊受訓,同一個基地,隔壁家的就出一些毛病,就是他們可能有些",
      "chunk_id": "aa1db64f-9158-47f5-a66e-f6d48717ad7e",
      "chunk_index": 74,
      "episode_id": "6864df05b8a9f5c81761b4b5",
      "original_filename": "RSS_1500839292_podcast_1321_EP308 _ .json",
      "collection_name": "RSS_1500839292",
      "chunk_length": 192
    },
    {
      "chunk_text": "一上飛機就開始吐,他就是一直吐就對了,你也不知道在吐啥小,反正他就是永遠都會吐,那也矯正不過來,最後面他就因為這樣被刷掉,那有些就是飛的時候會很緊張,所以他四肢僵硬,有時候被罵腦筋空白,那這種也會直接被刷掉,所以看下來,我覺得他好像蠻喜歡那一種,很活的人,可是同時是你會遵循SOP,你不會有太多自己的想法,fly by book,這是很重要的一個觀念,就是你完全照書在操作,你不是一個risk taker,雖然老實講啦,那時候在學,",
      "chunk_id": "3f1b69da-673d-4ba7-b91b-3b5daa7f02ff",
      "chunk_index": 75,
      "episode_id": "6864df05b8a9f5c81761b4b5",
      "original_filename": "RSS_1500839292_podcast_1321_EP308 _ .json",
      "collection_name": "RSS_1500839292",
      "chunk_length": 216
    },
    {
      "chunk_text": "飛航的人格測驗的時候,我們大家都知道,你不可以是一個risk taker,他問你喜不喜歡跳傘,靠北林北是傘兵,只是我還是要寫不喜歡,我最討厭這種冒險的東西,我不覺得這是騙人啦,就是我知道我做這個行業,我就必須要這樣子嘛,所以你大概要了解一下說他們會想要什麼樣的人,那再來就是面試,面試也蠻關鍵的啦,盡量不要說什麼,我是在體驗世界的,因為這個張國偉,K棟會直接跟你講說會直接被刷掉,我相信你這樣講會被刷掉,你可以講說你是為了錢,你是有什麼飛行的熱情或什麼的,",
      "chunk_id": "8e9e1c01-a0ba-41f0-83fa-c48b350034da",
      "chunk_index": 76,
      "episode_id": "6864df05b8a9f5c81761b4b5",
      "original_filename": "RSS_1500839292_podcast_1321_EP308 _ .json",
      "collection_name": "RSS_1500839292",
      "chunk_length": 228
    },
    {
      "chunk_text": "你是想幫工作創造價值都可以,但是不要講說我是來這邊想要什麼體驗世界看看世界,人家幹嘛要付錢讓你出去玩喔,對吧,所以面試稍微努力一下啦,那其他的我覺得都隨緣啦,你去考的時候就會明白我在講什麼,所以各家都丟,然後丟下去之後呢,就看你可以上哪一家,因為就我看來,像有些朋友上A沒上B,然後上C沒上A之類的,那像我自己是,滑航在第二關我就被刷掉,那長榮有過到後面,",
      "chunk_id": "fcd5c854-21a5-465a-afc4-0c425fe8eea5",
      "chunk_index": 77,
      "episode_id": "6864df05b8a9f5c81761b4b5",
      "original_filename": "RSS_1500839292_podcast_1321_EP308 _ .json",
      "collection_name": "RSS_1500839292",
      "chunk_length": 178
    },
    {
      "chunk_text": "威航呢是直接過到底,威航上就直接去了,就沒有等長榮了,所以就覺得反正哪邊可以上就去哪邊,然後剛好選到一個籤王倒掉的那一家,但如果現在是繼續在長榮飛會比較好嗎,我覺得也很難說,因為長榮他就是一個比較知名的,像是當兵的環境啦,他們比較一板一眼,聽說有蠻多人是已經跑去受那種大飛機訓的,那可是因為他的內務整理不好,或是說所謂的紀律不好,起床時間沒有固定還怎麼樣,就因為這樣被刷掉喔,所以各家的風格其實都不太好,",
      "chunk_id": "a036345d-f231-4323-afa1-14c1727c9739",
      "chunk_index": 78,
      "episode_id": "6864df05b8a9f5c81761b4b5",
      "original_filename": "RSS_1500839292_podcast_1321_EP308 _ .json",
      "collection_name": "RSS_1500839292",
      "chunk_length": 202
    },
    {
      "chunk_text": "那我覺得也不用花太多心思去想這樣的東西,反正就考了再說,因為他真的沒有公式啊,不然就不會說什麼有些人AB上,C沒上,有些人BC上,A沒上,有些人只有C上,有些人只有A上,就比較少看到那種全雷達的啦,至少就我自己的經驗是這樣子,所以代表你其實也不太確定他的標準到底是怎麼樣,因為如果說真的有一個完美的標準,應該這個人每家都要上,可能比較少看到這樣的一個狀況,好下面這個硬體白痴,他說除了救我五星吹起來,小弟的媽媽在做台股掛號,沒有金融衍生品的菜籃族,",
      "chunk_id": "a3edf4bc-4b2d-4c8b-b291-abe4eb8d1c57",
      "chunk_index": 79,
      "episode_id": "6864df05b8a9f5c81761b4b5",
      "original_filename": "RSS_1500839292_podcast_1321_EP308 _ .json",
      "collection_name": "RSS_1500839292",
      "chunk_length": 224
    },
    {
      "chunk_text": "他最近想換一台用來交易的電腦,掛號預算50K,請問比較推薦筆電還是桌機,以及有什麼需要注意的硬體需求嗎?小弟本身對於硬體一問三不知,想請主委開示,PS想問最近有沒有新一代iPad Pro的相關消息,今年這款太爛了,那再想要等到明年再買,還是接受現在的不完美,最後祝主委全家聖誕快樂,好沒問題既然你都問了,那我就看下一集有沒有機會或下下集,反正我會去幫你問一下iPad Pro有沒有什麼樣的東西啊,",
      "chunk_id": "a83694c0-569e-4604-b4d0-cbad0aa6a22f",
      "chunk_index": 80,
      "episode_id": "6864df05b8a9f5c81761b4b5",
      "original_filename": "RSS_1500839292_podcast_1321_EP308 _ .json",
      "collection_name": "RSS_1500839292",
      "chunk_length": 198
    },
    {
      "chunk_text": "目前我們有傳到的就是說iPhone下一代會改很大啦,所以等等黨的勝利可能真的要等到,雖然每一代都說會改很大,每一代都說會弄什麼屏下指紋辨識,轉Type-C什麼都一直講啦,但這一次應該是真的啦,聽說除了Type-C的採用之外,也有很多新的功能,酷的功能都會在下一代的iPhone拿出來啦,所以下一代iPhone是還蠻值得期待的,那iPad Pro是沒有聽到,但是我再去了解看看,因為本來iPad對我們來說也不是太重要的一個產品,",
      "chunk_id": "901d71ab-3f7a-43a0-8e2f-c65e32721061",
      "chunk_index": 81,
      "episode_id": "6864df05b8a9f5c81761b4b5",
      "original_filename": "RSS_1500839292_podcast_1321_EP308 _ .json",
      "collection_name": "RSS_1500839292",
      "chunk_length": 213
    },
    {
      "chunk_text": "我們會去追MacBook Pro,然後會去追iPhone,一個是量大,一個可能是M1、M2晶片,它是一個關鍵,電腦的這個硬體競爭也是很激烈的,所以我們看這兩個商品,iPad好,那我就再去了解一下,然後再來就是說,交易的電腦50K,隨便買都絕對可以啦,文書機就可以當交易電腦,因為它沒有在弄金融衍生品嘛,那它應該也不會有那種什麼tick tray之類的,所以我覺得硬體的要求應該就很低,簡單來講就是可以看盤,螢幕夠大就好了,",
      "chunk_id": "aa321c28-f3b1-4513-b89d-c0e1815f4eb2",
      "chunk_index": 82,
      "episode_id": "6864df05b8a9f5c81761b4b5",
      "original_filename": "RSS_1500839292_podcast_1321_EP308 _ .json",
      "collection_name": "RSS_1500839292",
      "chunk_length": 211
    },
    {
      "chunk_text": "就是你要給它一個螢幕夠大的環境,所以50K去組一台大螢幕外加主機,或是買一個中高階筆電都是綽綽有餘啦,隨便買就好,但是不要買蘋果系的,因為目前蘋果系的還是不太支援交易相關的東西,",
      "chunk_id": "cc1b7e2f-5025-4c22-beed-9bdcca0a902c",
      "chunk_index": 83,
      "episode_id": "6864df05b8a9f5c81761b4b5",
      "original_filename": "RSS_1500839292_podcast_1321_EP308 _ .json",
      "collection_name": "RSS_1500839292",
      "chunk_length": 89
    },
    {
      "chunk_text": "當然我是上次請主委彈吉他助朋友甚至快樂的聽眾,朋友也非常開心直呼特別,特別來還願感謝夢宮我老公,後來和這位多年不見的女性朋友約了出去吃飯看展,一開始氣氛是真的不錯,然而互動過程中也慢慢發現我們兩個的個性興趣,甚至喜歡的科目事物都南淵北測,最後自然是沒有走在一起,我也很快就放下了,但隨著平安夜聖誕節跨年逐漸逼近,想到不出意外又要一個人過節了,",
      "chunk_id": "889d0380-7eff-45c2-a03c-71058379557d",
      "chunk_index": 84,
      "episode_id": "6864df05b8a9f5c81761b4b5",
      "original_filename": "RSS_1500839292_podcast_1321_EP308 _ .json",
      "collection_name": "RSS_1500839292",
      "chunk_length": 171
    },
    {
      "chunk_text": "悲從中來,想問問主委遇到這種時候會如何調適心情呢?最後想請夢宮我老公再用電吉他選個悲創的Tone彈首Merry Christmas送給和我一樣魯魯過聖誕節的跨年聽眾,Cheers!不是啦,我跟你講,一個人過聖誕超爽的,你想要打摟打到天亮,想要玩四季玩到天亮,還是想要看球賽看到天亮都可以自選,我跟你講,單身的時候好好把握單身,不要想太多。",
      "chunk_id": "7b5404be-75dc-492b-81af-c4abf47de73b",
      "chunk_index": 85,
      "episode_id": "6864df05b8a9f5c81761b4b5",
      "original_filename": "RSS_1500839292_podcast_1321_EP308 _ .json",
      "collection_name": "RSS_1500839292",
      "chunk_length": 169
    },
    {
      "chunk_text": "下面一位,想要的ID被取走了,不同人,挨打我跟另外一個暱稱很像的是不同人啦,聽到他第一次留言被skip,後來又不死心的繼續留言時快笑死,我應該有幾個月沒留言了,正是想問,今年的盤因為經濟數據公布而跳上跳下,這在以前算是常見嗎?",
      "chunk_id": "f9acff1b-1f17-4e68-b882-d92365d8e754",
      "chunk_index": 86,
      "episode_id": "6864df05b8a9f5c81761b4b5",
      "original_filename": "RSS_1500839292_podcast_1321_EP308 _ .json",
      "collection_name": "RSS_1500839292",
      "chunk_length": 113
    },
    {
      "chunk_text": "如果難度滿分100分,IDA給今年幾分?85到90分吧,過往又會給幾分呢?過往其實投資都一向覺得沒有太難,好久沒有聽到第幾屆沉默循環,印象中自從上次第六屆到現在也滿一年了,Murder!到底要循環多久?希望大家都還活著,最近LoveGG大大有沒有什麼新的開始?哈哈哈,最後祝各位IU聖誕節快樂!",
      "chunk_id": "3e6f3496-277e-4091-8f72-a6619ffc46a1",
      "chunk_index": 87,
      "episode_id": "6864df05b8a9f5c81761b4b5",
      "original_filename": "RSS_1500839292_podcast_1321_EP308 _ .json",
      "collection_name": "RSS_1500839292",
      "chunk_length": 147
    },
    {
      "chunk_text": "這一屆沉默循環就是從11月12月,去年一直到現在沒有停過,開始越來越多人退出市場,對於市場是不聞不問,覺得再也不要玩股票了,算是一個比較長的沉默循環,等他走出來可能就是要看聯準會態度怎麼樣吧,因為他們家就是市場最大莊家,每次只要漲就出來一直瘋狂的昂聲,真的也就被他嚇到掉下去,",
      "chunk_id": "9bd58f95-6020-4c3c-be54-c4061f221d02",
      "chunk_index": 88,
      "episode_id": "6864df05b8a9f5c81761b4b5",
      "original_filename": "RSS_1500839292_podcast_1321_EP308 _ .json",
      "collection_name": "RSS_1500839292",
      "chunk_length": 138
    },
    {
      "chunk_text": "他們的權力很大,大到我覺得如同我之前評論的,今年好像你在玩中國股市一樣,就人治市場啊,他想要怎麼做就怎麼做,跟之前那種你想像中的市場該是,就是完全是遵隨企業的營收獲利,那考驗你的眼光是不太一樣的,現在比較像是一個總金盤啦,",
      "chunk_id": "e32d995a-f844-472b-987c-f15e0bfbca54",
      "chunk_index": 89,
      "episode_id": "6864df05b8a9f5c81761b4b5",
      "original_filename": "RSS_1500839292_podcast_1321_EP308 _ .json",
      "collection_name": "RSS_1500839292",
      "chunk_length": 111
    },
    {
      "chunk_text": "兄弟我跟你講,你這個東西繼續唸下去,你會繼續單身啦,這個就是以前無名小站那種寫幹文就是用這些東西,我不知道在打槍你,因為你是我的聽眾,所以我是真心想要幫你,不要再寫這樣子的東西了,",
      "chunk_id": "cc6f1ba8-d0ef-47dd-a93f-0a8538a2555d",
      "chunk_index": 90,
      "episode_id": "6864df05b8a9f5c81761b4b5",
      "original_filename": "RSS_1500839292_podcast_1321_EP308 _ .json",
      "collection_name": "RSS_1500839292",
      "chunk_length": 90
    },
    {
      "chunk_text": "我們男子漢就是應該坦蕩蕩,言簡意開,華仔都有教過,想你就打I miss you,愛你就打I love you,討厭你就打I hate you,想要復合就跟他說悲傷幹部,反正你就直接講,不要寫這麼多有的沒有的東西,真的,這個對你未來交友一點幫助都沒有,試著把簡單的東西簡單講,複雜的東西也簡單講,就是講完就好,我覺得我們男子漢就是這樣子啦,你不是在做Podcast節目,所以不要去寫這種論述的東西,真的,這是為了你好,那當然我也希望說你可以盡快的走出來啦,",
      "chunk_id": "a81fa2d5-6fcf-4cd7-a727-9e8f7e7acc28",
      "chunk_index": 91,
      "episode_id": "6864df05b8a9f5c81761b4b5",
      "original_filename": "RSS_1500839292_podcast_1321_EP308 _ .json",
      "collection_name": "RSS_1500839292",
      "chunk_length": 227
    },
    {
      "chunk_text": "我太勸和啦,我都勸分啦,有想要分手的或是已經分手的來這邊,我就叫你就是分手到底啊,破鏡我不相信會重圓啊,所以一切都是向前看好不好,那也祝你可以早日的走出來,",
      "chunk_id": "1937b732-6ac9-4160-bcc9-782814cf8d97",
      "chunk_index": 92,
      "episode_id": "6864df05b8a9f5c81761b4b5",
      "original_filename": "RSS_1500839292_podcast_1321_EP308 _ .json",
      "collection_name": "RSS_1500839292",
      "chunk_length": 78
    },
    {
      "chunk_text": "講到這種財經知識豐富,我也是感到悍言啊,當然我對於各項產品怎麼樣使用都非常了解,這個是基礎常識,在我看來這個叫基礎常識,它根本沒什麼好炫耀的,那對於各個產業的了解,那個是",
      "chunk_id": "cbb83252-83b2-4eef-95b6-7ac63c12dc97",
      "chunk_index": 93,
      "episode_id": "6864df05b8a9f5c81761b4b5",
      "original_filename": "RSS_1500839292_podcast_1321_EP308 _ .json",
      "collection_name": "RSS_1500839292",
      "chunk_length": 85
    },
    {
      "chunk_text": "博大精深,各項路各山,身為投資人,有時候我們想要切入一個新的產業,都要花很多的心思去了解,而且其實最後面會發現防守圈都是在固定幾個,像我自己可能在科技半導體零組件這樣子,那有時候會跨出去做一些什麼散裝航運啊,或是前陣子做原物料什麼的,那其實你說我們到底了解多深,我們也不敢講啊,至少比一般人深,這是肯定的,可是我們的AGE,我們賺錢的秘方真的是來自於說,就是我真的比大家了解的深嗎,我覺得不是,其實有時候就是賺",
      "chunk_id": "900326eb-918a-451b-996e-6ba498d74a6c",
      "chunk_index": 94,
      "episode_id": "6864df05b8a9f5c81761b4b5",
      "original_filename": "RSS_1500839292_podcast_1321_EP308 _ .json",
      "collection_name": "RSS_1500839292",
      "chunk_length": 205
    },
    {
      "chunk_text": "發那個題材的能力,",
      "chunk_id": "1c3209fb-416c-4be9-b207-a3c97f8a18ce",
      "chunk_index": 95,
      "episode_id": "6864df05b8a9f5c81761b4b5",
      "original_filename": "RSS_1500839292_podcast_1321_EP308 _ .json",
      "collection_name": "RSS_1500839292",
      "chunk_length": 9
    },
    {
      "chunk_text": "當因子做到好就可以非常的賺錢,它真的是有很多的因子疊加在一起,就是你不是長期投資就是巴菲特,你懂我意思嗎,你還要有一點,像有一本書信任編輯講的嘛,對人的眼光,然後再來就是你要有他的福春經,然後以及你要像他有鐵打的軟趴,所以他們腰斬了幾次,他們根本就沒有感覺,這個都是環環相扣的啦,那長輩那一輩有沒有這樣子,非常多,真的是很多,只是可能一般人沒有接觸到而已,非常厲害的產業前輩太多了,",
      "chunk_id": "a266d587-d902-4d20-8a16-096aaf820a25",
      "chunk_index": 96,
      "episode_id": "6864df05b8a9f5c81761b4b5",
      "original_filename": "RSS_1500839292_podcast_1321_EP308 _ .json",
      "collection_name": "RSS_1500839292",
      "chunk_length": 191
    },
    {
      "chunk_text": "那種50歲60歲甚至是快要70歲的,然後對於半導體,對於一些水泥鋼鐵原物料如數加增,這樣的人真的很多啦,只是可能因為資訊比較封閉,所以這樣的人不像現在有Facebook或什麼,它會冒出來嗎,一些什麼投資網紅之類的,其實可以冒出來的都是有點本事啦,除了那種你一看就知道他完全在傳教在騙人的,不然其實可以成為一方之主,都是有他一定的實力存在的,只是那個年代可能沒有",
      "chunk_id": "69985233-121e-4dbc-8531-57eee3bc4fd3",
      "chunk_index": 97,
      "episode_id": "6864df05b8a9f5c81761b4b5",
      "original_filename": "RSS_1500839292_podcast_1321_EP308 _ .json",
      "collection_name": "RSS_1500839292",
      "chunk_length": 180
    },
    {
      "chunk_text": "辦法有這種傳媒的力量讓這些人被發現,可是有沒有這樣子的人還真的蠻多的,至少以我自己的交友圈裡面,兩隻手都數不完,真的,就是說他們對於該產業特別了解,就專門在做那個,就像我之前跟大家聊到,有些人專門在做潤態集團第三季嘛,有些人專門每年就是可能下半年的時候開始做散裝航運嘛,那有些人是專門去弄金融股,或是也有那種半導體的前輩,他自己是可能中國一些大廠的大股東,那他知道狀況怎麼樣,他就在做",
      "chunk_id": "9431b5a9-7aea-4809-84b8-751f79cd50ee",
      "chunk_index": 98,
      "episode_id": "6864df05b8a9f5c81761b4b5",
      "original_filename": "RSS_1500839292_podcast_1321_EP308 _ .json",
      "collection_name": "RSS_1500839292",
      "chunk_length": 192
    },
    {
      "chunk_text": "半導體,其實怎麼講世界很大啦,真的是各式各樣的人都有,那這集我們先聊到這邊,因為我發現前面幾集都不小心講上五十分鐘,我還是希望把節目壓在四十幾分鐘,最好我覺得四十五分鐘以下,只有說因為我們節目前面講的長了,然後我看QA大家一直問,沒有念到就覺得很不好意思,所以會把它稍微延長一點,那大概以後就空在四十幾分鐘吧。",
      "chunk_id": "5747ea6d-7998-4fcc-aaf6-1bb4a83c1c71",
      "chunk_index": 99,
      "episode_id": "6864df05b8a9f5c81761b4b5",
      "original_filename": "RSS_1500839292_podcast_1321_EP308 _ .json",
      "collection_name": "RSS_1500839292",
      "chunk_length": 155
    }
  ],
  "original_text_length": 17092
}