{
  "filename": "RSS_1536242998_podcast_1321_EP1928吳淡如Ｘ歐陽昆博士創業家解決了中年人的痛點",
  "episode_id": "6860d9ad1a552e2cedaa8b65",
  "collection_name": "RSS_1536242998",
  "total_chunks": 45,
  "chunks": [
    {
      "chunk_id": "862f325a-664d-4a20-b40c-a3780ff2dcfa",
      "chunk_index": 0,
      "episode_id": "6860d9ad1a552e2cedaa8b65",
      "podcast_id": "1321",
      "podcast_name": "",
      "author": "",
      "category": "",
      "episode_title": "吳淡如Ｘ歐陽昆博士創業家解決了中年人的痛點",
      "duration": "",
      "published_date": "",
      "apple_rating": 0,
      "chunk_text": "這是泡泡染的廣告只要50元染一次15分鐘讓你的頭髮瞬間真的就會變年輕變得又黑又好看這就是我染我的白頭髮的方法我實在不喜歡白頭髮沒有任何的染髮劑沒有化學成分只是要不要告訴你泡泡染是我的臺大學弟詹乾輝他所研發的一盒",
      "embedding": [],
      "language": "zh",
      "created_at": "2025-07-10T14:47:55.771227",
      "source_model": "text-embedding-ada-002",
      "tags": "[\"教育\", \"刑事法律\"]"
    },
    {
      "chunk_id": "19af95f9-339e-4169-84aa-a125a802e431",
      "chunk_index": 1,
      "episode_id": "6860d9ad1a552e2cedaa8b65",
      "podcast_id": "1321",
      "podcast_name": "",
      "author": "",
      "category": "",
      "episode_title": "吳淡如Ｘ歐陽昆博士創業家解決了中年人的痛點",
      "duration": "",
      "published_date": "",
      "apple_rating": 0,
      "chunk_text": "可以染10次如果你是短頭髮的話而且他的化學藥劑都用在臺灣規定的最嚴格的最低標準之下請你看資訊欄的連結那麼你也可以把黑的加上紅的黑的加上咖啡的當然全黑的比較能夠遮蓋白髮這是最簡單的方法了15分鐘就好了請看資訊欄的連結10年來已經賣出了千萬包",
      "embedding": [],
      "language": "zh",
      "created_at": "2025-07-10T14:47:55.773763",
      "source_model": "text-embedding-ada-002",
      "tags": "[]"
    },
    {
      "chunk_id": "d17188f0-afda-4155-a43a-f5ec72828d80",
      "chunk_index": 2,
      "episode_id": "6860d9ad1a552e2cedaa8b65",
      "podcast_id": "1321",
      "podcast_name": "",
      "author": "",
      "category": "",
      "episode_title": "吳淡如Ｘ歐陽昆博士創業家解決了中年人的痛點",
      "duration": "",
      "published_date": "",
      "apple_rating": 0,
      "chunk_text": "今天是美好的一天我看見陽光燦爛今天是快樂的一天早上起牀歡迎收聽人生使用商學院我們今天來訪問的這一位這個公司好像換了名稱任裁國際的執行長歐陽坤教授你好",
      "embedding": [],
      "language": "zh",
      "created_at": "2025-07-10T14:47:55.776075",
      "source_model": "text-embedding-ada-002",
      "tags": "[\"快樂\", \"權利保障\", \"職涯\", \"時事\"]"
    },
    {
      "chunk_id": "ff5d70f0-3442-4e39-bb1c-fa13bf4cbcb2",
      "chunk_index": 3,
      "episode_id": "6860d9ad1a552e2cedaa8b65",
      "podcast_id": "1321",
      "podcast_name": "",
      "author": "",
      "category": "",
      "episode_title": "吳淡如Ｘ歐陽昆博士創業家解決了中年人的痛點",
      "duration": "",
      "published_date": "",
      "apple_rating": 0,
      "chunk_text": "聽眾朋友大家好我必須要讓大家的回憶recall一下他是能量貼布也就是遠紅外線光動能的科技的創始人37歲他就變成鄭教授而且是一個澎湖的小孩是吧故鄉沒有記錯很重要後來他當了教授之後教書的成績什麼科研的成績都很好但是董事長一聲令下他就變成了集團下面的",
      "embedding": [],
      "language": "zh",
      "created_at": "2025-07-10T14:47:55.778547",
      "source_model": "text-embedding-ada-002",
      "tags": "[\"科技\"]"
    },
    {
      "chunk_id": "a71cae17-b1fa-4893-986c-7bc82a548e10",
      "chunk_index": 4,
      "episode_id": "6860d9ad1a552e2cedaa8b65",
      "podcast_id": "1321",
      "podcast_name": "",
      "author": "",
      "category": "",
      "episode_title": "吳淡如Ｘ歐陽昆博士創業家解決了中年人的痛點",
      "duration": "",
      "published_date": "",
      "apple_rating": 0,
      "chunk_text": "某一個產品開發的負責人你現在還有在教課嗎有的我們現在還有在學校服務那在學校服務你在教什麼我現在在學校還是教的都是比較偏向創新產品開發這一類的課程那你一個禮拜只教兩個小時對主要時間好像挺不錯的主要時間還是在這個",
      "embedding": [],
      "language": "zh",
      "created_at": "2025-07-10T14:47:55.780933",
      "source_model": "text-embedding-ada-002",
      "tags": "[\"教育\"]"
    },
    {
      "chunk_id": "1d26dded-4262-4331-a0af-1349f8e06521",
      "chunk_index": 5,
      "episode_id": "6860d9ad1a552e2cedaa8b65",
      "podcast_id": "1321",
      "podcast_name": "",
      "author": "",
      "category": "",
      "episode_title": "吳淡如Ｘ歐陽昆博士創業家解決了中年人的痛點",
      "duration": "",
      "published_date": "",
      "apple_rating": 0,
      "chunk_text": "這個運營上面的管理比較多好那有關於能量貼布是你個人的專利嗎聽說你最近在研究一種貼布就叫做休眠時刻我一聽那個就知道說貼了可以助眠的是真的嗎是的這個應該源自於上次來上淡如姐的節目淡如姐有提到一個就是你會把奶貼在脖子後面比較好睡我們今天昨天晚上還有一塊在我的後頸椎那裡",
      "embedding": [],
      "language": "zh",
      "created_at": "2025-07-10T14:47:55.783438",
      "source_model": "text-embedding-ada-002",
      "tags": "[]"
    },
    {
      "chunk_id": "7abe715c-5cfd-4f6f-acc2-e170beddab9e",
      "chunk_index": 6,
      "episode_id": "6860d9ad1a552e2cedaa8b65",
      "podcast_id": "1321",
      "podcast_name": "",
      "author": "",
      "category": "",
      "episode_title": "吳淡如Ｘ歐陽昆博士創業家解決了中年人的痛點",
      "duration": "",
      "published_date": "",
      "apple_rating": 0,
      "chunk_text": "那因為有淡如姐上次有提到那我們也針對我們使用客羣做了一些調查那確實有蠻多客戶這樣子來使用那我們就找了一些睡眠專科醫師來做一些開會跟討論我們發現說這個後頸是一個副交感神經很重要的一個地方為什麼很多人在睡前去泡個熱水澡放鬆這些都讓這個副交感神經放鬆下來之後",
      "embedding": [],
      "language": "zh",
      "created_at": "2025-07-10T14:47:55.785877",
      "source_model": "text-embedding-ada-002",
      "tags": "[\"健康\"]"
    },
    {
      "chunk_id": "39a155ea-d4b3-4a58-960b-faa5c75c511d",
      "chunk_index": 7,
      "episode_id": "6860d9ad1a552e2cedaa8b65",
      "podcast_id": "1321",
      "podcast_name": "",
      "author": "",
      "category": "",
      "episode_title": "吳淡如Ｘ歐陽昆博士創業家解決了中年人的痛點",
      "duration": "",
      "published_date": "",
      "apple_rating": 0,
      "chunk_text": "會有助於這個睡眠你可以幫我解釋一下嗎為什麼我貼一個你們的能量的貼布就是在後頸跟身體跟頸部的交接的地方在學理上怎麼解釋還是我個人心理作用貼那裡我比較睡得著是因為我們的這個技術其實就是促進血液循環那這個光動能的貼布貼在你的後頸的部分它會讓這個地方的這個副交感神經放鬆",
      "embedding": [],
      "language": "zh",
      "created_at": "2025-07-10T14:47:55.788361",
      "source_model": "text-embedding-ada-002",
      "tags": "[\"科技\", \"健康\"]"
    },
    {
      "chunk_id": "b65135fa-0930-45a6-9e18-eb2ee6517b33",
      "chunk_index": 8,
      "episode_id": "6860d9ad1a552e2cedaa8b65",
      "podcast_id": "1321",
      "podcast_name": "",
      "author": "",
      "category": "",
      "episode_title": "吳淡如Ｘ歐陽昆博士創業家解決了中年人的痛點",
      "duration": "",
      "published_date": "",
      "apple_rating": 0,
      "chunk_text": "慢慢變好那在這個情況下你會感受到你比較放鬆那你就會自然而然就會睡得比較好那當然在這一次我們這個新的休眠時刻產品上面我們添加了這個美我們把這個美透過它能夠透過這個美的細化之後能夠讓它到精疲吸收那美我常常在很多這個中年以上的人喫的東西中看到什麼鈣美什麼迪片或者是美到底是對人體",
      "embedding": [],
      "language": "zh",
      "created_at": "2025-07-10T14:47:55.791057",
      "source_model": "text-embedding-ada-002",
      "tags": "[]"
    },
    {
      "chunk_id": "6fe53e12-2211-401c-84c8-e7f1f9ee20c0",
      "chunk_index": 9,
      "episode_id": "6860d9ad1a552e2cedaa8b65",
      "podcast_id": "1321",
      "podcast_name": "",
      "author": "",
      "category": "",
      "episode_title": "吳淡如Ｘ歐陽昆博士創業家解決了中年人的痛點",
      "duration": "",
      "published_date": "",
      "apple_rating": 0,
      "chunk_text": "有什麼樣的功能對因為在這個睡眠上面如果你是一個睡眠比較不好入睡的大概我們一般傾向用的幾種方式一個就是滋美錠那或者是放精油那當然還有很多人是去改變自己的枕頭這一類的方式那在我們這個產品裡面就是去做兩件事第一個我們讓你放鬆所以我們就放了我們的光動能技術加美美這個東西會安定你的這個副交感神經的穩定性",
      "embedding": [],
      "language": "zh",
      "created_at": "2025-07-10T14:47:55.793809",
      "source_model": "text-embedding-ada-002",
      "tags": "[\"科技\", \"健康\"]"
    },
    {
      "chunk_id": "ca600192-ca97-425a-95c8-86d402d67ab2",
      "chunk_index": 10,
      "episode_id": "6860d9ad1a552e2cedaa8b65",
      "podcast_id": "1321",
      "podcast_name": "",
      "author": "",
      "category": "",
      "episode_title": "吳淡如Ｘ歐陽昆博士創業家解決了中年人的痛點",
      "duration": "",
      "published_date": "",
      "apple_rating": 0,
      "chunk_text": "神經的這個傳導穩定性很多人都會知道有交感和副交感神經不過這恐怕還是要解釋一下交感神經是讓我們興奮的對不對副交感就是它的功能是讓我們把興奮稍微壓下來的那所以貼在你的後頸部因為它是掌控你的副交感神經的地方交接之處那麼其實你原來的貼布就有這樣的功能而且我說真的我只要貼其他的貼布本人",
      "embedding": [],
      "language": "zh",
      "created_at": "2025-07-10T14:47:55.796490",
      "source_model": "text-embedding-ada-002",
      "tags": "[]"
    },
    {
      "chunk_id": "22ed6225-c1a8-41a2-bc78-678ea767f49e",
      "chunk_index": 11,
      "episode_id": "6860d9ad1a552e2cedaa8b65",
      "podcast_id": "1321",
      "podcast_name": "",
      "author": "",
      "category": "",
      "episode_title": "吳淡如Ｘ歐陽昆博士創業家解決了中年人的痛點",
      "duration": "",
      "published_date": "",
      "apple_rating": 0,
      "chunk_text": "第一片應該不會過敏第二片我就開始過敏但是你們的東西就是因為它可能沒有止痛藥或者是其他的化學成分所以我的感受好一些到目前就不會過敏是應該有很多消費者這麼說吧因為我們在這個貼布上面我們的膠水我們的製程上面有機溶劑然後膠水從德國進口低致敏的膠水我們可以透過這樣的方式讓在這種比較潮濕比較熱的環境下比較讓",
      "embedding": [],
      "language": "zh",
      "created_at": "2025-07-10T14:47:55.799146",
      "source_model": "text-embedding-ada-002",
      "tags": "[\"權利保障\", \"時事\"]"
    },
    {
      "chunk_id": "45773c75-f1dd-42e4-ad7f-aff31c8cd3bf",
      "chunk_index": 12,
      "episode_id": "6860d9ad1a552e2cedaa8b65",
      "podcast_id": "1321",
      "podcast_name": "",
      "author": "",
      "category": "",
      "episode_title": "吳淡如Ｘ歐陽昆博士創業家解決了中年人的痛點",
      "duration": "",
      "published_date": "",
      "apple_rating": 0,
      "chunk_text": "亞洲的人的皮膚比較不會癢所以我們本來貼那個貼布貼久了會癢是因為膠水的過敏源的關係還是說我們天氣太熱的關係這個是一個共辯術就是熱它會流汗那這些膠水本身它有可能會導致它發癢所以熱又流汗然後你又貼著讓皮膚不能呼吸它就更容易會發癢那你如果現在就加了",
      "embedding": [],
      "language": "zh",
      "created_at": "2025-07-10T14:47:55.801699",
      "source_model": "text-embedding-ada-002",
      "tags": "[\"家庭\"]"
    },
    {
      "chunk_id": "89690478-4092-430d-a2c9-1d03f70b401a",
      "chunk_index": 13,
      "episode_id": "6860d9ad1a552e2cedaa8b65",
      "podcast_id": "1321",
      "podcast_name": "",
      "author": "",
      "category": "",
      "episode_title": "吳淡如Ｘ歐陽昆博士創業家解決了中年人的痛點",
      "duration": "",
      "published_date": "",
      "apple_rating": 0,
      "chunk_text": "推出了休眠時刻這個貼布以這個學者在做實驗通常也一定要經過比較嚴謹的過程你總不能叫老鼠睡你應該是叫人來睡那大家的後來收集出來的貢獻到底是什麼大家覺得有什麼感覺呢這個在很多的這種科學的研究上面有很多研究是透過在後頸照遠紅外線能夠去做這些",
      "embedding": [],
      "language": "zh",
      "created_at": "2025-07-10T14:47:55.804246",
      "source_model": "text-embedding-ada-002",
      "tags": "[\"感覺\"]"
    },
    {
      "chunk_id": "219e26ff-23f2-41d8-9b0e-be6ed0e52b9d",
      "chunk_index": 14,
      "episode_id": "6860d9ad1a552e2cedaa8b65",
      "podcast_id": "1321",
      "podcast_name": "",
      "author": "",
      "category": "",
      "episode_title": "吳淡如Ｘ歐陽昆博士創業家解決了中年人的痛點",
      "duration": "",
      "published_date": "",
      "apple_rating": 0,
      "chunk_text": "病人的睡眠實驗那另外就是用喫的美能夠去看看它是不是也有能夠幫助睡眠在很多醫學報上面都已經有明確的證據所以現在保健品已經很多了那在我們這個休眠時刻這一塊貼布上面第一個廣東的遠紅外線是已經是無非用自己的已經很成熟我們自己的技術第二個是這個美定我們透過SGS的這個晶皮吸收的這個測試好那我們確定說在這個貼布上面能夠有效",
      "embedding": [],
      "language": "zh",
      "created_at": "2025-07-10T14:47:55.806916",
      "source_model": "text-embedding-ada-002",
      "tags": "[\"科技\", \"健康\", \"司法程序\"]"
    },
    {
      "chunk_id": "2813f152-e369-4895-a1d3-f78ee1ccdd0b",
      "chunk_index": 15,
      "episode_id": "6860d9ad1a552e2cedaa8b65",
      "podcast_id": "1321",
      "podcast_name": "",
      "author": "",
      "category": "",
      "episode_title": "吳淡如Ｘ歐陽昆博士創業家解決了中年人的痛點",
      "duration": "",
      "published_date": "",
      "apple_rating": 0,
      "chunk_text": "的透過這個皮膚被吸收到你的體內那能夠跟我們在一般使用一樣就慢慢的釋放六個小時讓你可以在睡眠洗完澡貼上去然後慢慢的等待睡眠慢慢的吸收慢慢的讓副交感神經慢慢的去抑制它對就是透過這樣的機制其實我本來以為你是在研究住眠產品現在用喫的住眠我說真的已經很多了結果你是希望說都不用經過體內直接在",
      "embedding": [],
      "language": "zh",
      "created_at": "2025-07-10T14:47:55.809437",
      "source_model": "text-embedding-ada-002",
      "tags": "[\"希望\", \"健康\"]"
    },
    {
      "chunk_id": "10aa0997-11f6-44c7-8f06-00da7d4c234d",
      "chunk_index": 16,
      "episode_id": "6860d9ad1a552e2cedaa8b65",
      "podcast_id": "1321",
      "podcast_name": "",
      "author": "",
      "category": "",
      "episode_title": "吳淡如Ｘ歐陽昆博士創業家解決了中年人的痛點",
      "duration": "",
      "published_date": "",
      "apple_rating": 0,
      "chunk_text": "你的這個脖子上貼一下而且在你的脖子上貼的時候並不需要就是有的時候很多貼布裡面止痛藥是很可怕也有人告訴我我們以前不能說哪一家啦就是電視廣告很多的那個其實止痛藥成分會引起其他的副作用是這些藥物進到體內晶皮吸收後當然都需要透過腎臟去代謝感染代謝這些長期使用對身體都是有影響的",
      "embedding": [],
      "language": "zh",
      "created_at": "2025-07-10T14:47:55.811917",
      "source_model": "text-embedding-ada-002",
      "tags": "[\"刑事法律\"]"
    },
    {
      "chunk_id": "50c966de-a970-4f95-b1e5-78bfc41a96ce",
      "chunk_index": 17,
      "episode_id": "6860d9ad1a552e2cedaa8b65",
      "podcast_id": "1321",
      "podcast_name": "",
      "author": "",
      "category": "",
      "episode_title": "吳淡如Ｘ歐陽昆博士創業家解決了中年人的痛點",
      "duration": "",
      "published_date": "",
      "apple_rating": 0,
      "chunk_text": "好那當然你這個比如說我剛剛有跟歐陽博士說過能量貼布很好可是它真的一片算起來很大片但平均那一片算起來還挺貴的是不是其實在你們專利是自己的如果可以大量生產的話那其實價格就壓下來跟其他的那些止痛貼布的護塵盒就會出來因為其實現在的中年人也是他們可能需要貼布也很顧慮它的安全性",
      "embedding": [],
      "language": "zh",
      "created_at": "2025-07-10T14:47:55.814535",
      "source_model": "text-embedding-ada-002",
      "tags": "[]"
    },
    {
      "chunk_id": "df9b6879-4e2b-48e3-b1da-dfc2fab43eae",
      "chunk_index": 18,
      "episode_id": "6860d9ad1a552e2cedaa8b65",
      "podcast_id": "1321",
      "podcast_name": "",
      "author": "",
      "category": "",
      "episode_title": "吳淡如Ｘ歐陽昆博士創業家解決了中年人的痛點",
      "duration": "",
      "published_date": "",
      "apple_rating": 0,
      "chunk_text": "可是如果真的價格挺高的話那麼他可能就會覺得每天貼耶負擔有挺大的對不對所以上次因為大儒姐的建議之後我們也出了這個小片包裝的我發現我的建議對你們公司很重要很重要因為大的那個我要剪成四片所以我們回去之後就研發這個小的而且我們這個檢查也有做一些特殊的調整因為大儒姐這代表是市場的這個很重要的這個指標",
      "embedding": [],
      "language": "zh",
      "created_at": "2025-07-10T14:47:55.817061",
      "source_model": "text-embedding-ada-002",
      "tags": "[\"權利保障\", \"職涯\"]"
    },
    {
      "chunk_id": "071d691e-c64b-497f-8271-462725c95909",
      "chunk_index": 19,
      "episode_id": "6860d9ad1a552e2cedaa8b65",
      "podcast_id": "1321",
      "podcast_name": "",
      "author": "",
      "category": "",
      "episode_title": "吳淡如Ｘ歐陽昆博士創業家解決了中年人的痛點",
      "duration": "",
      "published_date": "",
      "apple_rating": 0,
      "chunk_text": "就是老年化社會的指標就開始要貼貼布它又很容易過敏這樣子那麼你現在的就是大部分的時間看起來在學校是兩個小時那其實大部分時間都還是在你的公司裡面做研發然後管它的產品的創新怎麼包裝定價這個很困難嗎這個不是很困難但是它需要花很多心力要把它做得很仔細",
      "embedding": [],
      "language": "zh",
      "created_at": "2025-07-10T14:47:55.819517",
      "source_model": "text-embedding-ada-002",
      "tags": "[\"權利保障\", \"教育\", \"職涯\", \"時事\"]"
    },
    {
      "chunk_id": "b3391fb7-05b8-4ef9-ab7b-66c27b4ac7b4",
      "chunk_index": 20,
      "episode_id": "6860d9ad1a552e2cedaa8b65",
      "podcast_id": "1321",
      "podcast_name": "",
      "author": "",
      "category": "",
      "episode_title": "吳淡如Ｘ歐陽昆博士創業家解決了中年人的痛點",
      "duration": "",
      "published_date": "",
      "apple_rating": 0,
      "chunk_text": "因為在我們的產品上面它的品管它的這些原料的控管包含我們的原料的製造我們都全部在臺灣自己來經手來處理那當然這些就所說的事情就會比較多好那其實的確本來的貼布就有那個休眠時刻的功能我不知道大家有沒有試試看我是很習慣我本來是以為不是貼布的作用而是可能那個地方就是溫度的改變",
      "embedding": [],
      "language": "zh",
      "created_at": "2025-07-10T14:47:55.822080",
      "source_model": "text-embedding-ada-002",
      "tags": "[\"健康\"]"
    },
    {
      "chunk_id": "02467fc8-ca31-40e1-a848-21008d3153de",
      "chunk_index": 21,
      "episode_id": "6860d9ad1a552e2cedaa8b65",
      "podcast_id": "1321",
      "podcast_name": "",
      "author": "",
      "category": "",
      "episode_title": "吳淡如Ｘ歐陽昆博士創業家解決了中年人的痛點",
      "duration": "",
      "published_date": "",
      "apple_rating": 0,
      "chunk_text": "鎮定一下那麼我的整個集中力就不會一直在腦袋那邊鬼想就會集中在我的頸椎不知不覺我就會比較容易睡著那現在就有了專門針對休眠的產品可是像你們公司因為我知道歐陽博士以前是打籃球運動員對不對打棒壘球打棒壘球運動員你很注重襪子所以你們公司剛開始的起始",
      "embedding": [],
      "language": "zh",
      "created_at": "2025-07-10T14:47:55.824569",
      "source_model": "text-embedding-ada-002",
      "tags": "[\"權利保障\", \"職涯\", \"健康\"]"
    },
    {
      "chunk_id": "ffee694d-36e5-4e38-9cde-4638d5b7d657",
      "chunk_index": 22,
      "episode_id": "6860d9ad1a552e2cedaa8b65",
      "podcast_id": "1321",
      "podcast_name": "",
      "author": "",
      "category": "",
      "episode_title": "吳淡如Ｘ歐陽昆博士創業家解決了中年人的痛點",
      "duration": "",
      "published_date": "",
      "apple_rating": 0,
      "chunk_text": "是做襪子的做紗線紗線不是襪子好那做這個紗線那也有襪子已經推出很久了吧這產品後來又在有被改良嗎有我們當然因為其實我們覺得很有趣的襪子的市場一般我們就用成民生用襪那我們收到了很多有趣的feedback例如有一個使用者他一天他要走",
      "embedding": [],
      "language": "zh",
      "created_at": "2025-07-10T14:47:55.827090",
      "source_model": "text-embedding-ada-002",
      "tags": "[]"
    },
    {
      "chunk_id": "8e215c13-9f8e-4ecf-bed4-99ac7572a2af",
      "chunk_index": 23,
      "episode_id": "6860d9ad1a552e2cedaa8b65",
      "podcast_id": "1321",
      "podcast_name": "",
      "author": "",
      "category": "",
      "episode_title": "吳淡如Ｘ歐陽昆博士創業家解決了中年人的痛點",
      "duration": "",
      "published_date": "",
      "apple_rating": 0,
      "chunk_text": "5公里以上的路就我啊然後他就會覺得說這襪子可不可以幫我們改良得更堅固耐用那我們就也很感謝他我們就一直不斷的寄給他免費的說那你每天可不可以你就跑步繼續走那5公里然後他就跟我說那他的朋友還有那種什麼跑更遠的就我們跑全馬的我們就送給他每天讓他去跑然後我們就去改變我們的織法改變我們的測試",
      "embedding": [],
      "language": "zh",
      "created_at": "2025-07-10T14:47:55.829693",
      "source_model": "text-embedding-ada-002",
      "tags": "[]"
    },
    {
      "chunk_id": "9aead091-2e0d-449f-80fe-e53337331ddb",
      "chunk_index": 24,
      "episode_id": "6860d9ad1a552e2cedaa8b65",
      "podcast_id": "1321",
      "podcast_name": "",
      "author": "",
      "category": "",
      "episode_title": "吳淡如Ｘ歐陽昆博士創業家解決了中年人的痛點",
      "duration": "",
      "published_date": "",
      "apple_rating": 0,
      "chunk_text": "幫我們的這個主體的厚度你這裡上面可以打這個促進血液循環嗎還有那個抑菌消臭是因為那個紗線因為你本來是一個處理紗線的公司紗線裡面織入遠紅外線的物質嗎是的我們把光動能放到我們的紗線裡面然後把它抽出來所以這些的字眼都是因為我們有這個合格的檢測然後我們纔能夠去寫到這些字眼可是像這些動能有些人會",
      "embedding": [],
      "language": "zh",
      "created_at": "2025-07-10T14:47:55.832265",
      "source_model": "text-embedding-ada-002",
      "tags": "[\"權利保障\", \"職涯\"]"
    },
    {
      "chunk_id": "f0f365ff-6828-4a94-b15a-25d41b7de6b9",
      "chunk_index": 25,
      "episode_id": "6860d9ad1a552e2cedaa8b65",
      "podcast_id": "1321",
      "podcast_name": "",
      "author": "",
      "category": "",
      "episode_title": "吳淡如Ｘ歐陽昆博士創業家解決了中年人的痛點",
      "duration": "",
      "published_date": "",
      "apple_rating": 0,
      "chunk_text": "叫這個大家趕快買新產品因為裡面不管你支出什麼他的效用那個半衰期一定會出現有的會叫你一年那換一遍可是在我看起來你的襪子是就是彈性很好而且他其實到了一年兩年我其實已經那個襪子的抽屜裡有用兩年的其實他比較不會變硬為什麼主要是這樣我們的紗線不是泡藥水來做抗菌處理因為我們主要都是在襪子本身的",
      "embedding": [],
      "language": "zh",
      "created_at": "2025-07-10T14:47:55.834807",
      "source_model": "text-embedding-ada-002",
      "tags": "[]"
    },
    {
      "chunk_id": "7a120527-9669-40ee-afdc-b8cd268bfd70",
      "chunk_index": 26,
      "episode_id": "6860d9ad1a552e2cedaa8b65",
      "podcast_id": "1321",
      "podcast_name": "",
      "author": "",
      "category": "",
      "episode_title": "吳淡如Ｘ歐陽昆博士創業家解決了中年人的痛點",
      "duration": "",
      "published_date": "",
      "apple_rating": 0,
      "chunk_text": "這個紗線上面在抽紗的過程中放入我們要剛做的抗菌的粉末或是光動能的粉末不是用藥水後製所以第一個剛剛大容姐提到的所以這有差別有差因為他不會硬第二個他不會失效我們的紗線例如說像我們的布料我們都要定期檢測我們兩三年或隨期用兩三年去測這個布的遠紅外線放射率基本上都不太會有改變那科勒斯的襪子我們到底可以穿幾年",
      "embedding": [],
      "language": "zh",
      "created_at": "2025-07-10T14:47:55.837381",
      "source_model": "text-embedding-ada-002",
      "tags": "[]"
    },
    {
      "chunk_id": "ec55744a-5bb1-412e-a2be-2b2a5647ba9e",
      "chunk_index": 27,
      "episode_id": "6860d9ad1a552e2cedaa8b65",
      "podcast_id": "1321",
      "podcast_name": "",
      "author": "",
      "category": "",
      "episode_title": "吳淡如Ｘ歐陽昆博士創業家解決了中年人的痛點",
      "duration": "",
      "published_date": "",
      "apple_rating": 0,
      "chunk_text": "才需要丟掉用的都還沒有壞主要應該是這樣看個人的清潔還有使用上面他有沒有破損不然的話如果說他都是定期清潔整理基本上他的抗菌他的光動能的遠紅外線他是可以一直持續的保持在這個紗線上你有常常觀察商品的定價像你那能量貼布我覺得就比市價的貼布貴但你的襪子明明搞了這麼久",
      "embedding": [],
      "language": "zh",
      "created_at": "2025-07-10T14:47:55.839877",
      "source_model": "text-embedding-ada-002",
      "tags": "[\"整理\"]"
    },
    {
      "chunk_id": "6194427e-fc15-4098-a863-7f51009807af",
      "chunk_index": 28,
      "episode_id": "6860d9ad1a552e2cedaa8b65",
      "podcast_id": "1321",
      "podcast_name": "",
      "author": "",
      "category": "",
      "episode_title": "吳淡如Ｘ歐陽昆博士創業家解決了中年人的痛點",
      "duration": "",
      "published_date": "",
      "apple_rating": 0,
      "chunk_text": "那麼多的科技在裡頭又比外面的那種沒有什麼功能的運動棉襪其實是比較便宜的你有發現嗎是你們真的也有人注意到這一點了嗎對因為只要市場上面講到這種能量相關的襪子其實都賣的非常貴但是我們是當初本來是希望說我們的襪子是可以有很多人都可以買得下去所以我們的這個部分因為紗線是我們起家的",
      "embedding": [],
      "language": "zh",
      "created_at": "2025-07-10T14:47:55.842439",
      "source_model": "text-embedding-ada-002",
      "tags": "[\"科技\", \"希望\", \"健康\"]"
    },
    {
      "chunk_id": "f0f3478e-88e1-4f68-ac84-5d9cc450316a",
      "chunk_index": 29,
      "episode_id": "6860d9ad1a552e2cedaa8b65",
      "podcast_id": "1321",
      "podcast_name": "",
      "author": "",
      "category": "",
      "episode_title": "吳淡如Ｘ歐陽昆博士創業家解決了中年人的痛點",
      "duration": "",
      "published_date": "",
      "apple_rating": 0,
      "chunk_text": "技術所以我們當初一開始最大的推廣都在這個織物上面所以價格相對會比較好是因為我們是自己抽的其實是紡織公司對不對你背後管的那個就是負責生產這種特殊紗線的公司也等於是一條龍那你們的這個也有做內衣庫這又是怎麼一回事其實產品還蠻看起來好像分類蠻多的但是都是集中在光動能就遠紅外線",
      "embedding": [],
      "language": "zh",
      "created_at": "2025-07-10T14:47:55.845043",
      "source_model": "text-embedding-ada-002",
      "tags": "[\"科技\", \"權利保障\", \"職涯\"]"
    },
    {
      "chunk_id": "b35c4451-d4a8-4e99-afba-0942f0ef22c2",
      "chunk_index": 30,
      "episode_id": "6860d9ad1a552e2cedaa8b65",
      "podcast_id": "1321",
      "podcast_name": "",
      "author": "",
      "category": "",
      "episode_title": "吳淡如Ｘ歐陽昆博士創業家解決了中年人的痛點",
      "duration": "",
      "published_date": "",
      "apple_rating": 0,
      "chunk_text": "的織品上面因為光動能這個技術來這邊第三次我們這個技術就是不是一般的遠紅外線是我們的遠紅外線的強度我們都達到94%以上所以是一個比較高強度的遠紅外線我們把它稱為光動能那我們做在這些民生用品上當然我們發現一個特性我們都沒有做太多外表的會有跟快時尚有關的主要都是跟內衣褲",
      "embedding": [],
      "language": "zh",
      "created_at": "2025-07-10T14:47:55.847575",
      "source_model": "text-embedding-ada-002",
      "tags": "[\"科技\"]"
    },
    {
      "chunk_id": "8ddcc58c-5fc3-48cc-bb2e-d8f269d6c10f",
      "chunk_index": 31,
      "episode_id": "6860d9ad1a552e2cedaa8b65",
      "podcast_id": "1321",
      "podcast_name": "",
      "author": "",
      "category": "",
      "episode_title": "吳淡如Ｘ歐陽昆博士創業家解決了中年人的痛點",
      "duration": "",
      "published_date": "",
      "apple_rating": 0,
      "chunk_text": "就是長得都很簡單襪子基本上也都黑的因為我們就是希望我們的東西是可以讓大家真的穿在貼身的地方而且有效因為要碰到皮膚然後可以讓你穿了真的會幫助你做血液循環讓你放鬆這樣子的一個公司的一個定位所以在去年其實花了最多心力是我們把官網我們的App各方面做了一個重新調整我們把公司定位在分用",
      "embedding": [],
      "language": "zh",
      "created_at": "2025-07-10T14:47:55.850126",
      "source_model": "text-embedding-ada-002",
      "tags": "[\"希望\", \"權利保障\", \"職涯\"]"
    },
    {
      "chunk_id": "6ec98e85-4c5b-46c6-9fc9-063bba394809",
      "chunk_index": 32,
      "episode_id": "6860d9ad1a552e2cedaa8b65",
      "podcast_id": "1321",
      "podcast_name": "",
      "author": "",
      "category": "",
      "episode_title": "吳淡如Ｘ歐陽昆博士創業家解決了中年人的痛點",
      "duration": "",
      "published_date": "",
      "apple_rating": 0,
      "chunk_text": "有解勞這個四個字眼上面來重新定定位我們公司的確如果是做功能性的就不需要做什麼快時尚因為其實消費者的功能真的他所需求沒有那麼多樣性所謂的如果你是要穿出去炫給大家好看的在家裡就不用穿那在家裡穿的這些東西大家比較願意花錢是因為他可以長長久久的穿我相信穿你們的襪子或者是內衣褲的都是",
      "embedding": [],
      "language": "zh",
      "created_at": "2025-07-10T14:47:55.852631",
      "source_model": "text-embedding-ada-002",
      "tags": "[\"權利保障\", \"職涯\"]"
    },
    {
      "chunk_id": "c6cb026e-8dde-4ec1-be9e-acfc542644e6",
      "chunk_index": 33,
      "episode_id": "6860d9ad1a552e2cedaa8b65",
      "podcast_id": "1321",
      "podcast_name": "",
      "author": "",
      "category": "",
      "episode_title": "吳淡如Ｘ歐陽昆博士創業家解決了中年人的痛點",
      "duration": "",
      "published_date": "",
      "apple_rating": 0,
      "chunk_text": "很划算的因為到現在應該都沒有壞吧可是為什麼我們的內衣褲要有光動能你沒有比如說像內衣還有T恤可能也需要光動能就是一邊運動的時候有點按摩作用這樣子因為主要是這樣我們都全部都把它做在Underwear上面是內裡面的部分你運動的時候很多女性他其實還是都裡面會有在穿一件內搭所以我們還是都",
      "embedding": [],
      "language": "zh",
      "created_at": "2025-07-10T14:47:55.855199",
      "source_model": "text-embedding-ada-002",
      "tags": "[\"健康\"]"
    },
    {
      "chunk_id": "dc708800-d821-4441-a568-a389cb98d6a1",
      "chunk_index": 34,
      "episode_id": "6860d9ad1a552e2cedaa8b65",
      "podcast_id": "1321",
      "podcast_name": "",
      "author": "",
      "category": "",
      "episode_title": "吳淡如Ｘ歐陽昆博士創業家解決了中年人的痛點",
      "duration": "",
      "published_date": "",
      "apple_rating": 0,
      "chunk_text": "可是在這個裡面的這一件衣服或褲子上外面的運動服上面我們其實現在有殺線只是我們後來因為以公司的市場評估下我們沒有去做外面這一件事因為他的每一個季度的汰換率還有我們必須要設計很多的樣式其實這個對於一般的品牌經營上面是其實現在全世界的這種服裝品牌經營上面是很辛苦的你不要走快時尚我很知道快時尚",
      "embedding": [],
      "language": "zh",
      "created_at": "2025-07-10T14:47:55.857774",
      "source_model": "text-embedding-ada-002",
      "tags": "[\"權利保障\", \"職涯\", \"健康\"]"
    },
    {
      "chunk_id": "54f54666-9590-45c9-bf0f-b3bf73cf6a23",
      "chunk_index": 35,
      "episode_id": "6860d9ad1a552e2cedaa8b65",
      "podcast_id": "1321",
      "podcast_name": "",
      "author": "",
      "category": "",
      "episode_title": "吳淡如Ｘ歐陽昆博士創業家解決了中年人的痛點",
      "duration": "",
      "published_date": "",
      "apple_rating": 0,
      "chunk_text": "後面的路就是賺到了一大堆的庫存好那麼歐陽博士現在你也還在大學上課然後也在工廠裡面在當這個等於行政職你覺得哪一樣工作對你而言比較困難當然是在業界上班的這個過程是比較辛苦的因為本來在一家公司來管理那後來當然現在目前",
      "embedding": [],
      "language": "zh",
      "created_at": "2025-07-10T14:47:55.860197",
      "source_model": "text-embedding-ada-002",
      "tags": "[\"權利保障\", \"教育\", \"職涯\"]"
    },
    {
      "chunk_id": "f6ac4470-2a01-426a-b1a1-9c68cdb50797",
      "chunk_index": 36,
      "episode_id": "6860d9ad1a552e2cedaa8b65",
      "podcast_id": "1321",
      "podcast_name": "",
      "author": "",
      "category": "",
      "episode_title": "吳淡如Ｘ歐陽昆博士創業家解決了中年人的痛點",
      "duration": "",
      "published_date": "",
      "apple_rating": 0,
      "chunk_text": "又再增加了另外一家就主要是工廠我們把我們的技術變成工廠來真正自己生產多了這個製造管理這個部分就會從以前學校很多都是天馬行空的創新就是你現在要管那個上游殺線對不對造產品以前只管產品現在連工廠都交給你對超殺這樣薪水應該變高兩倍不好查",
      "embedding": [],
      "language": "zh",
      "created_at": "2025-07-10T14:47:55.862660",
      "source_model": "text-embedding-ada-002",
      "tags": "[\"科技\", \"教育\"]"
    },
    {
      "chunk_id": "0603eae0-915f-4893-b0f7-9a1e2c2113b7",
      "chunk_index": 37,
      "episode_id": "6860d9ad1a552e2cedaa8b65",
      "podcast_id": "1321",
      "podcast_name": "",
      "author": "",
      "category": "",
      "episode_title": "吳淡如Ｘ歐陽昆博士創業家解決了中年人的痛點",
      "duration": "",
      "published_date": "",
      "apple_rating": 0,
      "chunk_text": "在臺灣主要應該還是這樣我們都是以一個榮譽就可以有這個經驗來學習管理工廠跟公司那為你管工廠其實對一個學者而已還蠻困難你看起來勾引勾引會不會有一些老鳥就是覺得這是一個大學的老師就是不懂我們業界會不會遇到這樣的質疑讓你怎麼對付剛開始我確實也蠻擔心的但是後來我覺得我的管理方法",
      "embedding": [],
      "language": "zh",
      "created_at": "2025-07-10T14:47:55.865151",
      "source_model": "text-embedding-ada-002",
      "tags": "[\"權利保障\", \"教育\", \"職涯\"]"
    },
    {
      "chunk_id": "d506c91f-eae7-46fa-9920-b232e33ada8a",
      "chunk_index": 38,
      "episode_id": "6860d9ad1a552e2cedaa8b65",
      "podcast_id": "1321",
      "podcast_name": "",
      "author": "",
      "category": "",
      "episode_title": "吳淡如Ｘ歐陽昆博士創業家解決了中年人的痛點",
      "duration": "",
      "published_date": "",
      "apple_rating": 0,
      "chunk_text": "比較特殊是因為我的殺線是我研發我來做所以現場他們會理解我會懂他們在做什麼因為我也會到現場去尤其是剛開始我們在裝機臺裝調校設備我基本上是可以陪著我們的現場同仁一整天都待在那邊把東西弄好所以我認為親力親為在初期成立工廠的時候是很重要那裡面的核心員工的認同到後面你跟他講",
      "embedding": [],
      "language": "zh",
      "created_at": "2025-07-10T14:47:55.867661",
      "source_model": "text-embedding-ada-002",
      "tags": "[]"
    },
    {
      "chunk_id": "1fa98f7f-6aba-4c1a-aa1f-ff6e056595a7",
      "chunk_index": 39,
      "episode_id": "6860d9ad1a552e2cedaa8b65",
      "podcast_id": "1321",
      "podcast_name": "",
      "author": "",
      "category": "",
      "episode_title": "吳淡如Ｘ歐陽昆博士創業家解決了中年人的痛點",
      "duration": "",
      "published_date": "",
      "apple_rating": 0,
      "chunk_text": "他就會知道他能夠知道我講的話是我知道你在做什麼那你現在就要從研發很少人管這麼多的研發行政然後一直要管到後面的管銷還要自己出來當發言人這基本上是一件很忙碌的行為難怪我有一陣子想說這個不在乎行銷是賣得太好了嗎怎麼很久沒有看到這個人的出現沒有其實一直都有",
      "embedding": [],
      "language": "zh",
      "created_at": "2025-07-10T14:47:55.870203",
      "source_model": "text-embedding-ada-002",
      "tags": "[]"
    },
    {
      "chunk_id": "388fa8b7-d1e5-4b9b-986d-fc21cb75c705",
      "chunk_index": 40,
      "episode_id": "6860d9ad1a552e2cedaa8b65",
      "podcast_id": "1321",
      "podcast_name": "",
      "author": "",
      "category": "",
      "episode_title": "吳淡如Ｘ歐陽昆博士創業家解決了中年人的痛點",
      "duration": "",
      "published_date": "",
      "apple_rating": 0,
      "chunk_text": "惦記著淡如姐所以今天來了那我再問你你覺得就是一個學者後來來做生意你最大的獲得是什麼你一定也有發現這中間的趣味嗎對不對不然就會說就是跟董事會說不好意思我就回去交出就好這我不管了是但最大獲得大概我覺得有一個很是讓我到現在為止我還非常有衝勁就是我覺得過去我們在談一個想法我們要把它做出來這件事落實是很困難的但我們現在是可以看到它落實",
      "embedding": [],
      "language": "zh",
      "created_at": "2025-07-10T14:47:55.872901",
      "source_model": "text-embedding-ada-002",
      "tags": "[\"董事會\"]"
    },
    {
      "chunk_id": "8733f036-aade-4c3f-938c-68b7e702cb19",
      "chunk_index": 41,
      "episode_id": "6860d9ad1a552e2cedaa8b65",
      "podcast_id": "1321",
      "podcast_name": "",
      "author": "",
      "category": "",
      "episode_title": "吳淡如Ｘ歐陽昆博士創業家解決了中年人的痛點",
      "duration": "",
      "published_date": "",
      "apple_rating": 0,
      "chunk_text": "到市場變成商品然後我最大的滿足點就是例如說有使用者來跟我說它這東西很棒那我就會更有動力想把它做得更好那當然有時候在這個商業上大家會說都是東西就做得太好就會很難賺錢因為很多細節很多功但我認為臺灣的整個質感一直在提升未來的臺灣也不會以CP值為王道我們未來一定會以更高的品質",
      "embedding": [],
      "language": "zh",
      "created_at": "2025-07-10T14:47:55.875548",
      "source_model": "text-embedding-ada-002",
      "tags": "[]"
    },
    {
      "chunk_id": "31082d7a-b7e5-486e-9b7d-d43a17d563bc",
      "chunk_index": 42,
      "episode_id": "6860d9ad1a552e2cedaa8b65",
      "podcast_id": "1321",
      "podcast_name": "",
      "author": "",
      "category": "",
      "episode_title": "吳淡如Ｘ歐陽昆博士創業家解決了中年人的痛點",
      "duration": "",
      "published_date": "",
      "apple_rating": 0,
      "chunk_text": "標準一定是有感纔能夠回購不然你剛開始賣多便宜如果大家消費者覺得沒有用還真的以後也沒有用好那麼這次請到歐陽博士來講他的創業過程他剛剛已經很阿莎力的說因為我嫌他的能量貼布很有用但太貴他願意來衝一個量對不對還有加上新的休眠時刻其實他襪子已經很便宜了但是其實消費者你說不重視",
      "embedding": [],
      "language": "zh",
      "created_at": "2025-07-10T14:47:55.878230",
      "source_model": "text-embedding-ada-002",
      "tags": "[\"權利保障\", \"職涯\"]"
    },
    {
      "chunk_id": "2274c4fe-5abb-4cb3-b8fa-4098cfbfc639",
      "chunk_index": 43,
      "episode_id": "6860d9ad1a552e2cedaa8b65",
      "podcast_id": "1321",
      "podcast_name": "",
      "author": "",
      "category": "",
      "episode_title": "吳淡如Ｘ歐陽昆博士創業家解決了中年人的痛點",
      "duration": "",
      "published_date": "",
      "apple_rating": 0,
      "chunk_text": "CP值很好的東西如果更便宜有什麼不可以請大家看一下資訊欄的連結你可以體會一下他們的貼布的確是我用過我覺得臺灣最好的貼布至少我其實常常天天用不管涼感的還是熱感的其實我沒有什麼差別冬天我還是可以貼涼感就貼在後頸椎的地方還是覺得很舒服就這樣子",
      "embedding": [],
      "language": "zh",
      "created_at": "2025-07-10T14:47:55.880821",
      "source_model": "text-embedding-ada-002",
      "tags": "[]"
    },
    {
      "chunk_id": "a12a39b0-57d5-4f02-a436-e3cd2ca7e754",
      "chunk_index": 44,
      "episode_id": "6860d9ad1a552e2cedaa8b65",
      "podcast_id": "1321",
      "podcast_name": "",
      "author": "",
      "category": "",
      "episode_title": "吳淡如Ｘ歐陽昆博士創業家解決了中年人的痛點",
      "duration": "",
      "published_date": "",
      "apple_rating": 0,
      "chunk_text": "可以試試看我所說的感覺不必再貼一些傳統的裡面有止痛藥的貼布了謝謝歐陽博士謝謝詹姆傑謝謝大家",
      "embedding": [],
      "language": "zh",
      "created_at": "2025-07-10T14:47:55.883060",
      "source_model": "text-embedding-ada-002",
      "tags": "[\"感覺\"]"
    }
  ],
  "standardized_at": "2025-07-10T17:27:04.570089"
}